Workbook

Sheet Summary
A1: Allied fleet status at start of 25 Dec 1941 (from wpae021 incoming file, game date 12/25/41)
A2: Counts below are live formulas over the Active Ships, Task Forces, Reinforcements and Losses tabs.
A4: Active Allied ships | B4: =COUNTA('Active Ships'!A2:A1289) -> 1288
A5: at sea in task forces | B5: =COUNTIF('Active Ships'!F2:F1289,">=0") -> 913
A6: in port | B6: =COUNTIF('Active Ships'!E2:E1289,"In port*") -> 375
A7: Allied task forces | B7: =COUNTA('Task Forces'!A2:A252) -> 251
A8: Damaged ships (any sys/float/engine damage) | B8: =COUNTA('Damaged Ships'!A2:A577) -> 576
A9: Ships on fire | B9: =COUNTIF('Active Ships'!S2:S1289,">0") -> 2
A10: Ships below 25% fuel | B10: =COUNTIFS('Active Ships'!K2:K1289,"<0.25",'Active Ships'!J2:J1289,">0") -> 34
A11: Ships lost (in these saves) | B11: =COUNTA(Losses!A2:A94) -> 93
A12: Future reinforcements scheduled | B12: =COUNTA(Reinforcements!A2:A5734) -> 5733
A15: Active ships by type | D15: Active ships by nation
A16: xAK | B16: =COUNTIF('Active Ships'!B2:B1289,A16) -> 269 | D16: USA | E16: =COUNTIF('Active Ships'!D2:D1289,D16) -> 578
A17: xAP | B17: =COUNTIF('Active Ships'!B2:B1289,A17) -> 150 | D17: UK | E17: =COUNTIF('Active Ships'!D2:D1289,D17) -> 276
A18: xAKL | B18: =COUNTIF('Active Ships'!B2:B1289,A18) -> 126 | D18: Netherlands | E18: =COUNTIF('Active Ships'!D2:D1289,D18) -> 169
A19: AG | B19: =COUNTIF('Active Ships'!B2:B1289,A19) -> 77 | D19: Australia | E19: =COUNTIF('Active Ships'!D2:D1289,D19) -> 123
A20: DD | B20: =COUNTIF('Active Ships'!B2:B1289,A20) -> 77 | D20: Other Allied | E20: =COUNTIF('Active Ships'!D2:D1289,D20) -> 61
A21: TK | B21: =COUNTIF('Active Ships'!B2:B1289,A21) -> 71 | D21: India | E21: =COUNTIF('Active Ships'!D2:D1289,D21) -> 23
A22: SS | B22: =COUNTIF('Active Ships'!B2:B1289,A22) -> 69 | D22: Philippines | E22: =COUNTIF('Active Ships'!D2:D1289,D22) -> 21
A23: AMc | B23: =COUNTIF('Active Ships'!B2:B1289,A23) -> 74 | D23: New Zealand | E23: =COUNTIF('Active Ships'!D2:D1289,D23) -> 17
A24: PT | B24: =COUNTIF('Active Ships'!B2:B1289,A24) -> 44 | D24: Canada | E24: =COUNTIF('Active Ships'!D2:D1289,D24) -> 14
A25: AVP | B25: =COUNTIF('Active Ships'!B2:B1289,A25) -> 27 | D25: Free French | E25: =COUNTIF('Active Ships'!D2:D1289,D25) -> 6
A26: AM | B26: =COUNTIF('Active Ships'!B2:B1289,A26) -> 26
A27: APD | B27: =COUNTIF('Active Ships'!B2:B1289,A27) -> 22
A28: CL | B28: =COUNTIF('Active Ships'!B2:B1289,A28) -> 21
A29: AO | B29: =COUNTIF('Active Ships'!B2:B1289,A29) -> 21
A30: CA | B30: =COUNTIF('Active Ships'!B2:B1289,A30) -> 17
A31: AP | B31: =COUNTIF('Active Ships'!B2:B1289,A31) -> 15
A32: KV | B32: =COUNTIF('Active Ships'!B2:B1289,A32) -> 15
A33: PG | B33: =COUNTIF('Active Ships'!B2:B1289,A33) -> 14
A34: AKE | B34: =COUNTIF('Active Ships'!B2:B1289,A34) -> 13
A35: DMS | B35: =COUNTIF('Active Ships'!B2:B1289,A35) -> 13
A36: YP | B36: =COUNTIF('Active Ships'!B2:B1289,A36) -> 10
A37: BB | B37: =COUNTIF('Active Ships'!B2:B1289,A37) -> 10
A38: ACM | B38: =COUNTIF('Active Ships'!B2:B1289,A38) -> 10
A39: PC | B39: =COUNTIF('Active Ships'!B2:B1289,A39) -> 10
A40: AMC | B40: =COUNTIF('Active Ships'!B2:B1289,A40) -> 74
A41: HDML | B41: =COUNTIF('Active Ships'!B2:B1289,A41) -> 9
A42: AS | B42: =COUNTIF('Active Ships'!B2:B1289,A42) -> 9
A43: CM | B43: =COUNTIF('Active Ships'!B2:B1289,A43) -> 8
A44: DM | B44: =COUNTIF('Active Ships'!B2:B1289,A44) -> 8
A45: AVD | B45: =COUNTIF('Active Ships'!B2:B1289,A45) -> 7
A46: AE | B46: =COUNTIF('Active Ships'!B2:B1289,A46) -> 6
A47: CV | B47: =COUNTIF('Active Ships'!B2:B1289,A47) -> 5
A48: AGP | B48: =COUNTIF('Active Ships'!B2:B1289,A48) -> 5
A49: MTB | B49: =COUNTIF('Active Ships'!B2:B1289,A49) -> 5
A50: AK | B50: =COUNTIF('Active Ships'!B2:B1289,A50) -> 5
A51: AD | B51: =COUNTIF('Active Ships'!B2:B1289,A51) -> 5
A52: AV | B52: =COUNTIF('Active Ships'!B2:B1289,A52) -> 4
A53: AKV | B53: =COUNTIF('Active Ships'!B2:B1289,A53) -> 4
A54: AR | B54: =COUNTIF('Active Ships'!B2:B1289,A54) -> 3
A55: DE | B55: =COUNTIF('Active Ships'!B2:B1289,A55) -> 2
A56: BC | B56: =COUNTIF('Active Ships'!B2:B1289,A56) -> 1
A57: CVL | B57: =COUNTIF('Active Ships'!B2:B1289,A57) -> 1

Sheet Active Ships
A1: Ship | B1: Type | C1: Class | D1: Nation | E1: Location | F1: TF | G1: Captain | H1: Crew exp | I1: Fuel | J1: Max fuel | K1: Fuel % | L1: Endurance (nm) | M1: Max speed (kn) | N1: Sys dmg | O1: Float dmg | P1: Float major | Q1: Eng dmg | R1: Eng major | S1: Fire
A2: British Motorist | B2: TK | C2: Federal Type-E | D2: UK | E2: At sea, TF 18 (48,128) | F2: 18 | G2: Campbell G. | H2: 25 | I2: 1240 | J2: 1321 | K2: 0.93868282 | L2: 11264 | M2: 14 | N2: 5 | O2: 0 | P2: 0 | Q2: 1 | R2: 1 | S2: 0
A3: Bengalen | B3: xAK | C3: Euro K Cargo | D3: Netherlands | E3: At sea, TF 18 (48,128) | F3: 18 | G3: Blokzijl V. | H3: 19 | I3: 1309 | J3: 1366 | K3: 0.95827233 | L3: 17153 | M3: 14 | N3: 1 | O3: 0 | P3: 0 | Q3: 1 | R3: 1 | S3: 0
A4: La Cordillera | B4: xAK | C4: Euro M Cargo | D4: UK | E4: At sea, TF 18 (48,128) | F4: 18 | G4: Webster D. | H4: 15 | I4: 1212 | J4: 1288 | K4: 0.94099379 | L4: 11574 | M4: 14 | N4: 0 | O4: 0 | P4: 0 | Q4: 0 | R4: 0 | S4: 0
A5: Hong Peng | B5: xAP | C5: Straits/Hong | D5: UK | E5: At sea, TF 18 (48,128) | F5: 18 | G5: Goodwin W. | H5: 15 | I5: 835 | J5: 930 | K5: 0.89784946 | L5: 7003 | M5: 14 | N5: 0 | O5: 0 | P5: 0 | Q5: 0 | R5: 0 | S5: 0
A6: Skipjack | B6: SS | C6: Salmon | D6: USA | E6: At sea, TF 197 (79,88) Cagayan | F6: 197 | G6: Freeman, C.L. | H6: 55 | I6: 260 | J6: 314 | K6: 0.82802548 | L6: 9108 | M6: 21 | N6: 0 | O6: 0 | P6: 0 | Q6: 0 | R6: 0 | S6: 0
A7: Anniston City | B7: xAK | C7: Hog Island Cargo | D7: USA | E7: At sea, TF 199 (226,83) near San Diego | F7: 199 | G7: Allison N. | H7: 15 | I7: 934 | J7: 1440 | K7: 0.64861111 | L7: 9534 | M7: 12 | N7: 0 | O7: 0 | P7: 0 | Q7: 0 | R7: 0 | S7: 0
A8: Dewey | B8: DD | C8: Farragut | D8: USA | E8: At sea, TF 201 (209,92) | F8: 201 | G8: Chillingworth, C. | H8: 55 | I8: 476 | J8: 600 | K8: 0.79333333 | L8: 4561 | M8: 32 | N8: 1 | O8: 0 | P8: 0 | Q8: 0 | R8: 0 | S8: 0
A9: MacDonough | B9: DD | C9: Farragut | D9: USA | E9: At sea, TF 201 (209,92) | F9: 201 | G9: Dennett, E. | H9: 59 | I9: 478 | J9: 600 | K9: 0.79666667 | L9: 4580 | M9: 32 | N9: 1 | O9: 0 | P9: 0 | Q9: 0 | R9: 0 | S9: 0
A10: Phelps | B10: DD | C10: Porter | D10: USA | E10: At sea, TF 201 (209,92) | F10: 201 | G10: Beck, E. | H10: 58 | I10: 534 | J10: 635 | K10: 0.84094488 | L10: 6307 | M10: 34 | N10: 1 | O10: 0 | P10: 0 | Q10: 1 | R10: 1 | S10: 0
A11: Shaw | B11: DD | C11: Mahan | D11: USA | E11: At sea, TF 201 (209,92) | F11: 201 | G11: Jones, W. | H11: 61 | I11: 421 | J11: 522 | K11: 0.80651341 | L11: 5242 | M11: 35 | N11: 4 | O11: 0 | P11: 0 | Q11: 0 | R11: 0 | S11: 0
A12: Salmon | B12: SS | C12: Salmon | D12: USA | E12: At sea, TF 203 (72,90) Tawi Tawi | F12: 203 | G12: McKinney, E.B. | H12: 55 | I12: 247 | J12: 314 | K12: 0.7866242 | L12: 8652 | M12: 21 | N12: 0 | O12: 0 | P12: 0 | Q12: 0 | R12: 0 | S12: 0
A13: Seal | B13: SS | C13: Salmon | D13: USA | E13: At sea, TF 203 (72,90) Tawi Tawi | F13: 203 | G13: Hurd, K.C. | H13: 55 | I13: 247 | J13: 314 | K13: 0.7866242 | L13: 8652 | M13: 21 | N13: 1 | O13: 0 | P13: 0 | Q13: 0 | R13: 0 | S13: 0
... A914: Malda | B914: xAP | C914: Tasman/India | D914: UK | E914: At sea, TF 98 (30,34) | F914: 98 | G914: Galbraith B. | H914: 11 | I914: 1272 | J914: 1272 | K914: 1 | L914: 9700 | M914: 15 | N914: 0 | O914: 0 | P914: 0 | Q914: 0 | R914: 0 | S914: 0
A915: Vito | B915: xAK | C915: Euro M Cargo | D915: Other Allied | E915: In port: (104,195) | G915: Edge J. | H915: 20 | I915: 1288 | J915: 1288 | K915: 1 | L915: 12300 | M915: 14 | N915: 0 | O915: 0 | P915: 0 | Q915: 0 | R915: 0 | S915: 0
A916: Cosgrove | B916: AMc | C916: Castle Trawler | D916: New Zealand | E916: In port: (108,193) | G916: Burgess R. | H916: 15 | I916: 97 | J916: 97 | K916: 1 | L916: 1600 | M916: 11 | N916: 0 | O916: 0 | P916: 0 | Q916: 0 | R916: 0 | S916: 0
A917: Currell | B917: AMc | C917: Castle Trawler | D917: New Zealand | E917: In port: (108,193) | G917: Thompson R. | H917: 13 | I917: 97 | J917: 97 | K917: 1 | L917: 1600 | M917: 11 | N917: 0 | O917: 0 | P917: 0 | Q917: 0 | R917: 0 | S917: 0
A918: Arizonan | B918: AG | C918: Transmarine Tender | D918: USA | E918: In port: (112,191) | G918: Brinkley, N.S. | H918: 10 | I918: 1010 | J918: 1010 | K918: 1 | L918: 11000 | M918: 12 | N918: 1 | O918: 0 | P918: 0 | Q918: 0 | R918: 0 | S918: 0
A919: Atlanta City | B919: AG | C919: Isthmian Tender | D919: USA | E919: In port: (112,191) | G919: Shedlock, V.D. | H919: 11 | I919: 1320 | J919: 1320 | K919: 1 | L919: 13600 | M919: 12 | N919: 1 | O919: 0 | P919: 0 | Q919: 0 | R919: 0 | S919: 0
A920: Dakotan | B920: AG | C920: Isthmian Tender | D920: USA | E920: In port: (112,191) | G920: Boyles, E.V. | H920: 8 | I920: 1320 | J920: 1320 | K920: 1 | L920: 13600 | M920: 12 | N920: 1 | O920: 0 | P920: 0 | Q920: 0 | R920: 0 | S920: 0
A921: Puerto Rican | B921: AG | C921: Transmarine Tender | D921: USA | E921: In port: (112,191) | G921: Ruby, G.I. | H921: 4 | I921: 1010 | J921: 1010 | K921: 1 | L921: 11000 | M921: 12 | N921: 1 | O921: 0 | P921: 0 | Q921: 0 | R921: 0 | S921: 0
A922: Santa Rita | B922: AG | C922: Isthmian Tender | D922: USA | E922: In port: (112,191) | G922: Proffit, K.N. | H922: 5 | I922: 1320 | J922: 1320 | K922: 1 | L922: 13600 | M922: 12 | N922: 1 | O922: 0 | P922: 0 | Q922: 0 | R922: 0 | S922: 0
A923: Swan | B923: AVP | C923: Bird AVP | D923: USA | E923: In port: (113,140) | G923: Vaughn U. | H923: 18 | I923: 143 | J923: 200 | K923: 0.715 | L923: 4647 | M923: 14 | N923: 0 | O923: 0 | P923: 0 | Q923: 0 | R923: 0 | S923: 0
A924: Gale | B924: AMc | C924: Castle Trawler | D924: New Zealand | E924: In port: (132,160) | G924: Baker U. | H924: 15 | I924: 97 | J924: 97 | K924: 1 | L924: 1600 | M924: 11 | N924: 0 | O924: 0 | P924: 0 | Q924: 0 | R924: 0 | S924: 0
A925: Kingfisher | B925: AVP | C925: Bird AVP | D925: USA | E925: In port: (148,161) | G925: Wedemeyer, A.S. | H925: 32 | I925: 200 | J925: 200 | K925: 1 | L925: 6500 | M925: 14 | N925: 1 | O925: 0 | P925: 0 | Q925: 0 | R925: 0 | S925: 0
A926: Robin | B926: AM | C926: Bird | D926: USA | E926: In port: (164,112) | G926: Van Voorhis, H.V. | H926: 31 | I926: 200 | J926: 200 | K926: 1 | L926: 6500 | M926: 14 | N926: 0 | O926: 0 | P926: 0 | Q926: 0 | R926: 0 | S926: 0
... A1289: Niagara | B1289: AGP | C1289: Niagara | D1289: USA | E1289: In port: near Tulagi (114,138) | G1289: Dragoon, M.W. | H1289: 16 | I1289: 69 | J1289: 500 | K1289: 0.138 | L1289: 828 | M1289: 12 | N1289: 0 | O1289: 0 | P1289: 0 | Q1289: 0 | R1289: 0 | S1289: 0

Sheet Task Forces
A1: TF | B1: Mission | C1: Current hex / place | D1: Home port | E1: Destination | F1: Next hexes on path | G1: Ships | H1: Flagship | I1: Lowest fuel % | J1: Damaged ships | K1: Ship list
A2: 18 | B2: Transport (CS convoy) | C2: (48,128) | D2: Soerabaja (56,104) | E2: Soerabaja (56,104) | F2: 48,127 > 48,126 > 48,125 > 49,124 > 49,123 | G2: 4 | H2: TK British Motorist | I2: 0.9 | J2: 2 | K2: xAK La Cordillera, xAP Hong Peng, xAK Bengalen, TK British Motorist
A3: 43 | B3: Cargo (?) | C3: (58,117) | D3: Soerabaja (56,104) | E3: Broome (62,127) | F3: 59,118 > 58,119 > 59,120 > 59,121 > 60,122 | G3: 1 | H3: xAKL Shinai | I3: 0.44 | J3: 1 | K3: xAKL Shinai
A4: 98 | B4: Escort (?) | C4: (30,34) | D4: near Madurai (28,40) | F4: 29,35 > 29,36 > 28,37 > 28,38 > 27,39 | G4: 4 | H4: xAP Doumer | I4: 1 | J4: 0 | K4: xAP Doumer, xAP Malda, AMc Poona, AMc Madura
A5: 197 | B5: Submarine | C5: (79,88) Cagayan | D5: Darwin (76,124) | F5: 80,88 > 80,88 > 80,88 > 80,88 > 80,88 | G5: 1 | H5: SS Skipjack | I5: 0.83 | J5: 0 | K5: SS Skipjack
A6: 199 | B6: Transport | C6: (226,83) near San Diego | D6: San Diego (227,78) | E6: San Diego (227,78) | F6: 227,82 > 226,81 > 227,80 > 226,79 > 227,78 | G6: 1 | H6: xAK Anniston City | I6: 0.65 | J6: 0 | K6: xAK Anniston City
A7: 201 | B7: ASW Combat | C7: (209,92) | D7: San Diego (227,78) | E7: San Diego (227,78) | F7: 210,92 > 210,91 > 211,91 > 212,90 > 213,90 | G7: 4 | H7: DD Phelps | I7: 0.79 | J7: 4 | K7: DD Shaw, DD Phelps, DD Dewey, DD MacDonough
A8: 203 | B8: Submarine | C8: (72,90) Tawi Tawi | D8: Darwin (76,124) | F8: 71,89 > 71,89 > 71,89 > 71,89 > 70,93 | G8: 3 | H8: SS Sturgeon | I8: 0.79 | J8: 2 | K8: SS Salmon, SS Seal, SS Sturgeon
A9: 210 | B9: Troop transport (?) | C9: (65,106) Makassar | D9: near Denpasar (59,109) | E9: near Denpasar (59,109) | F9: 64,107 > 63,107 > 63,108 > 62,108 > 61,108 | G9: 2 | H9: xAKL Schouten | I9: 0.77 | J9: 0 | K9: xAKL Schouten, xAKL Sipirok
A10: 216 | B10: Troop transport (?) | C10: (58,111) near Denpasar | D10: Soerabaja (56,104) | E10: Broome (62,127) | F10: 59,112 > 58,113 > 59,114 > 58,115 > 59,116 | G10: 3 | H10: xAK Empire Hamble | I10: 0.71 | J10: 0 | K10: xAK Empire Hamble, xAK Gorgon, xAK Lowana
A11: 218 | B11: Troop transport (?) | C11: (9,13) | D11: Abadan (39,3) | E11: (11,62) | F11: 10,14 > 9,15 > 10,16 > 9,17 > 10,18 | G11: 1 | H11: xAP Tairea | I11: 0.82 | J11: 0 | K11: xAP Tairea
A12: 219 | B12: Escort (?) | C12: (45,106) | D12: Colombo (29,48) | E12: Colombo (29,48) | F12: 44,106 > 43,106 > 42,106 > 41,106 > 40,106 | G12: 4 | H12: BC Repulse | I12: 0.78 | J12: 1 | K12: BC Repulse, DD Stronghold, DD Thracian, DD Jupiter
A13: 220 | B13: Transport | C13: (226,107) | D13: Pearl Harbor (180,107) | E13: Pearl Harbor (180,107) | F13: 225,107 > 224,107 > 223,107 > 222,107 > 221,107 | G13: 1 | H13: xAK Wilhelmina | I13: 0.98 | J13: 0 | K13: xAK Wilhelmina
A14: 222 | B14: Troop transport (?) | C14: (61,106) | D14: Makassar (65,106) | E14: Makassar (65,106) | F14: 62,106 > 63,106 > 64,106 > 65,106 > 61,106 | G14: 3 | H14: xAP Siberg | I14: 0.95 | J14: 0 | K14: xAP Rochussen, xAP Rooseboom, xAP Siberg
A15: 223 | B15: Troop transport (?) | C15: (72,121) near Darwin | D15: Soerabaja (56,104) | E15: Soerabaja (56,104) | F15: 72,120 > 71,120 > 70,119 > 69,119 > 69,118 | G15: 9 | H15: AM Ballarat | I15: 0.83 | J15: 8 | K15: AM Ballarat, xAP Glenorchy, xAP Kota Radja, xAP Kota Pinang, xAP Tjisaroea, xAKL Patris, xAK Tjikandi, xAK Tjikarang, xAP Van Overstraten
A16: 225 | B16: Transport | C16: (5,51) | D16: Cape Town (2,67) | E16: Cape Town (2,67) | F16: 4,51 > 4,51 > 4,51 > 4,51 > 4,51 | G16: 3 | H16: xAK Howra | I16: 0.56 | J16: 0 | K16: xAK Steel Maker, xAK Erinpura, xAK Howra
A17: 226 | B17: Transport | C17: (226,107) | D17: Pearl Harbor (180,107) | E17: Pearl Harbor (180,107) | F17: 225,107 > 224,107 > 223,107 > 222,107 > 221,107 | G17: 1 | H17: xAK Maliko | I17: 1 | J17: 0 | K17: xAK Maliko
A18: 230 | B18: Escort (?) | C18: (216,70) near San Francisco | D18: Alameda (219,70) | E18: Alameda (219,70) | F18: 217,70 > 218,70 > 219,70 > 214,70 > 215,70 | G18: 4 | H18: BB Oklahoma | I18: 0.51 | J18: 4 | K18: BB Nevada, BB Oklahoma, DD Helm, DD Patterson
A19: 232 | B19: Transport | C19: (57,113) | D19: (49,141) | E19: (49,141) | F19: 57,114 > 56,115 > 56,116 > 55,117 > 55,118 | G19: 1 | H19: xAKL Princess of Negros | I19: 0.91 | J19: 0 | K19: xAKL Princess of Negros
A20: 233 | B20: Troop transport (?) | C20: (56,104) Soerabaja | D20: Soerabaja (56,104) | E20: (57,129) | F20: 56,105 > 57,105 > 58,106 > 57,107 > 57,108 | G20: 2 | H20: xAP Kota Gede | I20: 0.45 | J20: 0 | K20: xAP Kota Gede, xAP Speelman
A21: 234 | B21: Submarine | C21: (99,121) | D21: Sydney (90,167) | E21: Sydney (90,167) | F21: 100,122 > 100,123 > 101,124 > 100,125 > 101,126 | G21: 1 | H21: SS Tarpon | I21: 0.65 | J21: 1 | K21: SS Tarpon
A22: 235 | B22: Submarine | C22: (80,94) near Davao | D22: Darwin (76,124) | F22: 79,94 > 79,94 > 79,94 > 80,95 > 80,95 | G22: 1 | H22: SS S-40 | I22: 0.51 | J22: 0 | K22: SS S-40
A23: 237 | B23: Transport | C23: (188,120) | D23: Pearl Harbor (180,107) | F23: 189,120 > 189,119 > 190,119 > 191,118 > 192,118 | G23: 1 | H23: AO Brazos | I23: 0.98 | J23: 1 | K23: AO Brazos
A24: 239 | B24: Transport (CS convoy) | C24: (226,83) near San Diego | D24: San Diego (227,78) | E24: San Diego (227,78) | F24: 227,82 > 226,81 > 227,80 > 226,79 > 227,78 | G24: 4 | H24: xAK Makua | I24: 0.95 | J24: 0 | K24: xAK Liloa, xAK Mahimahi, xAK Makua, xAK Mana
A25: 240 | B25: Submarine | C25: (84,89) near Siargao | D25: Darwin (76,124) | F25: 84,90 > 84,90 > 84,90 > 84,90 > 85,86 | G25: 1 | H25: SS Spearfish | I25: 0.83 | J25: 1 | K25: SS Spearfish
A26: 242 | B26: Surface Combat | C26: (139,170) | D26: Sydney (90,167) | E26: Sydney (90,167) | F26: 138,170 > 137,169 > 137,168 > 136,168 > 135,168 | G26: 1 | H26: CL Trenton | I26: 0.34 | J26: 1 | K26: CL Trenton
A27: 247 | B27: Transport | C27: (150,144) | D27: Pearl Harbor (180,107) | E27: Pearl Harbor (180,107) | F27: 151,144 > 151,143 > 152,143 > 153,142 > 153,141 | G27: 10 | H27: xAP Nairana | I27: 0.51 | J27: 4 | K27: xAK Dumosa, xAK Kekerangu, xAP Nairana, xAK Cardross, xAK Era, xAK Goulburn, xAK Mernoo, xAK Mundalla, xAK Period, xAK Ulooloo
A28: 248 | B28: Submarine | C28: (52,85) Tandjoengpinang | D28: Colombo (29,48) | F28: 52,84 > 52,84 > 52,84 > 52,84 > 52,84 | G28: 1 | H28: SS K IX | I28: 0.73 | J28: 0 | K28: SS K IX
A29: 249 | B29: Transport | C29: (36,5) | D29: Aden (20,3) | E29: Aden (20,3) | F29: 37,6 > 38,6 > 38,7 > 39,7 > 40,8 | G29: 5 | H29: xAK Durenda | I29: 1 | J29: 1 | K29: xAK Delawarean, xAK West Cawthon, xAK West Isleta, xAK Birminghan City, xAK Durenda
A30: 252 | B30: Submarine | C30: (84,88) near Dinagat | D30: Darwin (76,124) | F30: 84,87 > 84,87 > 84,87 > 84,87 > 84,87 | G30: 3 | H30: SS Stingray | I30: 0.82 | J30: 0 | K30: SS Perch, SS Pickerel, SS Stingray
A31: 256 | B31: Submarine | C31: (74,123) near Darwin | D31: Darwin (76,124) | F31: 75,124 > 76,124 > 75,120 > 74,121 > 74,122 | G31: 1 | H31: SS S-41 | I31: 0.16 | J31: 1 | K31: SS S-41
A32: 258 | B32: Submarine | C32: (83,90) near Siargao | D32: Darwin (76,124) | F32: 82,89 > 82,89 > 82,89 > 82,89 > 82,89 | G32: 1 | H32: SS Saury | I32: 0.84 | J32: 1 | K32: SS Saury
A33: 267 | B33: Submarine | C33: (83,86) near Dinagat | D33: Darwin (76,124) | F33: 82,86 > 82,86 > 82,86 > 82,86 > 85,88 | G33: 1 | H33: SS S-37 | I33: 0.59 | J33: 1 | K33: SS S-37
A34: 269 | B34: Transport (CS convoy) | C34: (175,150) | D34: near San Diego (225,76) | E34: Sydney (90,167) | F34: 174,151 > 174,152 > 173,153 > 173,154 > 175,149 | G34: 6 | H34: TK Mobilstation | I34: 0.86 | J34: 4 | K34: TK Alfred Clegg, TK Mobilfuel, TK Mobilstation, TK California Standard, TK Pat Doheny, TK Manzanillo
A35: 271 | B35: Escort (?) | C35: (201,92) | D35: (211,55) | E35: (211,55) | F35: 201,91 > 201,90 > 201,89 > 201,88 > 201,87 | G35: 8 | H35: BB West Virginia | I35: 0.47 | J35: 5 | K35: BB West Virginia, BB Arizona, DD Bagley, DD Cassin, DD Downes, KV Quesnel, KV Wetaskiwin, KV Chilliwack
A36: 272 | B36: Submarine | C36: (78,121) | D36: Darwin (76,124) | F36: 78,122 > 77,123 > 76,123 > 76,124 > 79,119 | G36: 1 | H36: SS Sailfish | I36: 0.73 | J36: 1 | K36: SS Sailfish
A37: 273 | B37: Submarine | C37: (78,88) near Cagayan | D37: Darwin (76,124) | F37: 79,88 > 79,88 > 79,88 > 79,88 > 79,88 | G37: 1 | H37: SS Sargo | I37: 0.84 | J37: 0 | K37: SS Sargo
A38: 274 | B38: Transport (CS convoy) | C38: (56,104) Soerabaja | D38: Soerabaja (56,104) | E38: (49,141) | F38: 56,105 > 57,105 > 58,106 > 57,107 > 57,108 | G38: 2 | H38: TK Merula | I38: 1 | J38: 1 | K38: TK Pan Europa, TK Merula
A39: 279 | B39: Submarine | C39: (82,78) near Polillo | D39: Darwin (76,124) | F39: 81,77 > 81,77 > 81,77 > 81,77 > 81,77 | G39: 1 | H39: SS Permit | I39: 0.8 | J39: 0 | K39: SS Permit
A40: 283 | B40: Surface Combat | C40: (209,92) | D40: San Diego (227,78) | E40: San Diego (227,78) | F40: 210,92 > 210,91 > 211,91 > 212,90 > 213,90 | G40: 6 | H40: DD Conyngham | I40: 0.61 | J40: 4 | K40: DD Case, DD Conyngham, DD Hull, DD Aylwin, DD Allen, DD Chew
A41: 284 | B41: Escort (?) | C41: (209,51) near Victoria | D41: near Bremerton (212,52) | F41: 210,51 > 211,51 > 212,52 | G41: 1 | H41: AMc Armentieres | I41: 1 | J41: 0 | K41: AMc Armentieres
A42: 285 | B42: Transport | C42: (227,78) San Diego | D42: San Diego (227,78) | F42: 226,79 > 225,79 > 225,80 > 224,80 > 223,81 | G42: 2 | H42: AP Crescent City | I42: 1 | J42: 0 | K42: AP Crescent City, xAK Alcoa Pennant
A43: 289 | B43: Submarine | C43: (92,144) Townsville | D43: Sydney (90,167) | E43: Sydney (90,167) | F43: 93,144 > 93,145 > 94,145 > 95,146 > 95,147 | G43: 3 | H43: SS Snapper | I43: 1 | J43: 0 | K43: SS Snapper, SS Seawolf, SS S-38
A44: 291 | B44: Transport (CS convoy) | C44: (180,111) | D44: Pearl Harbor (180,107) | E44: Sydney (90,167) | F44: 181,112 > 180,113 > 181,114 > 180,115 > 181,116 | G44: 15 | H44: CA Minneapolis | I44: 0.97 | J44: 4 | K44: CA New Orleans, CA Minneapolis, CL Raleigh, CL Detroit, CL Phoenix, CL Honolulu, DD Dale, DD Monaghan, AS Pelias, AV Curtiss, AV Tangier, AVD Thornton, AO Neosho, AK Castor, TK Gulfhawk
A45: 292 | B45: Transport (CS convoy) | C45: (133,157) | D45: Pearl Harbor (180,107) | E45: Sydney (90,167) | F45: 132,157 > 131,157 > 130,157 > 130,158 > 129,159 | G45: 8 | H45: AE Pyro | I45: 0.72 | J45: 3 | K45: AO Ramapo, AE Pyro, AG Argonne, AG Vega, AG Arctic, AG Antares, TK Gulfland, xAK Hoegh Merchant
A46: 293 | B46: Escort (?) | C46: (142,150) | D46: Luganville (120,150) | F46: 141,150 > 140,150 > 139,150 > 138,150 > 137,150 | G46: 17 | H46: AV Wright | I46: 0.56 | J46: 11 | K46: AV Wright, AD Dobbin, AD Whitney, AD Rigel, AVD McFarland, PT PT-20, PT PT-21, PT PT-22, PT PT-23, PT PT-24, PT PT-25, PT PT-26, PT PT-27, PT PT-28, PT PT-29, PT PT-30, PT PT-42
A47: 294 | B47: Troop transport (?) | C47: (120,150) Luganville | D47: near Mare' (115,160) | E47: near Mare' (115,160) | F47: 119,151 > 119,152 > 118,153 > 118,154 > 117,155 | G47: 8 | H47: xAP Republic | I47: 0.51 | J47: 5 | K47: xAP Chaumont, xAP Republic, xAK Anshun, xAK Yunnan, xAK Iron Baron, xAK Iron Chieftan, xAK Momba, xAK Theofano Livanos
A48: 295 | B48: Local Minesweeping | C48: (29,36) | D48: near Madurai (28,40) | F48: 28,37 > 28,38 > 27,39 > 28,40 > 29,33 | G48: 2 | H48: AMc Agra | I48: 1 | J48: 1 | K48: AMc Agra, AMc Calcutta
A49: 297 | B49: Transport (CS convoy) | C49: (12,76) | D49: Abadan (39,3) | E49: Perth (49,147) | F49: 12,77 > 12,78 > 12,79 > 12,80 > 12,81 | G49: 2 | H49: TK Athelstane | I49: 0.69 | J49: 0 | K49: xAK Ikauna, TK Athelstane
A50: 298 | B50: Transport (CS convoy) | C50: (33,18) | D50: Abadan (39,3) | E50: Abadan (39,3) | F50: 32,17 > 32,16 > 31,15 > 31,14 > 30,13 | G50: 1 | H50: TK Vivi | I50: 0.88 | J50: 1 | K50: TK Vivi
A51: 299 | B51: Transport | C51: (73,122) near Darwin | D51: Soerabaja (56,104) | E51: (89,124) | F51: 74,122 > 74,121 > 75,121 > 76,121 > 77,122 | G51: 9 | H51: xAK Hanyang | I51: 0.72 | J51: 7 | K51: xAKL Sagoland, xAKL Anakan, xAKL Dos Hermanos, xAKL Elcano, xAKL Escalante R, xAKL Taurus, xAK Hanyang, xAKL Kanchow, xAK Ravnaas
A52: 300 | B52: Escort (?) | C52: (63,99) near Balikpapan | D52: Soerabaja (56,104) | E52: Soerabaja (56,104) | F52: 63,100 > 62,101 > 62,102 > 61,102 > 60,102 | G52: 2 | H52: CL Boise | I52: 0.51 | J52: 2 | K52: CL Boise, DD Evertsen
A53: 301 | B53: Submarine | C53: (226,107) | D53: Pearl Harbor (180,107) | E53: Pearl Harbor (180,107) | F53: 225,107 > 224,107 > 223,107 > 222,107 > 221,107 | G53: 1 | H53: SS Gato | I53: 1 | J53: 0 | K53: SS Gato
A54: 306 | B54: Transport (CS convoy) | C54: (28,40) near Madurai | D54: near Madurai (28,40) | E54: (11,62) | F54: 27,41 > 26,41 > 26,42 > 25,42 > 24,43 | G54: 2 | H54: xAKL Elout | I54: 1 | J54: 2 | K54: xAKL Buijskes, xAKL Elout
A55: 308 | B55: Transport (CS convoy) | C55: (177,136) | D55: San Francisco (218,70) | E55: Christmas Island (174,141) | F55: 176,137 > 176,138 > 175,139 > 175,140 > 174,141 | G55: 3 | H55: TK Elsa | I55: 0.17 | J55: 2 | K55: TK William Sunoco, xAKL Nebraskan, TK Elsa
A56: 311 | B56: Escort (?) | C56: (56,113) | D56: Perth (49,147) | E56: Perth (49,147) | F56: 57,114 > 56,115 > 56,116 > 55,117 > 55,118 | G56: 1 | H56: DD Thanet | I56: 0.42 | J56: 0 | K56: DD Thanet
A57: 312 | B57: Transport | C57: (160,146) | D57: Pearl Harbor (180,107) | E57: Pearl Harbor (180,107) | F57: 161,146 > 161,145 > 162,144 > 162,143 > 163,142 | G57: 1 | H57: xAKL Kailua | I57: 0.44 | J57: 0 | K57: xAKL Kailua
A58: 313 | B58: Surface Combat | C58: (48,132) | D58: Perth (49,147) | E58: Perth (49,147) | F58: 47,133 > 47,134 > 47,135 > 47,136 > 47,137 | G58: 3 | H58: CL Mauritius | I58: 0.37 | J58: 3 | K58: CL Mauritius, DD Encounter, DD Isis
A59: 314 | B59: Surface Combat | C59: (5,102) | D59: Cape Town (2,67) | E59: Cape Town (2,67) | F59: 4,102 > 4,102 > 4,102 > 4,102 > 4,102 | G59: 1 | H59: BB Prince of Wales | I59: 0.67 | J59: 1 | K59: BB Prince of Wales
A60: 316 | B60: Transport (CS convoy) | C60: (160,133) | D60: San Francisco (218,70) | E60: Sydney (90,167) | F60: 160,134 > 159,135 > 159,136 > 158,137 > 158,138 | G60: 3 | H60: TK Mobilgas | I60: 0.89 | J60: 2 | K60: TK Mobilgas, TK Connecticut, TK H. M. Storey
... A65: 321 | B65: Escort (?) | C65: (70,123) | D65: Darwin (76,124) | E65: Darwin (76,124) | F65: 71,123 > 72,124 > 73,124 > 74,124 > 75,124 | G65: 6 | H65: CA Houston | I65: 0.6 | J65: 6 | K65: CA Houston, CL Marblehead, MTB MTB 7, MTB MTB 9, MTB MTB 26, MTB MTB 27
A66: 322 | B66: Minesweeping (?) | C66: (209,51) near Victoria | D66: near Victoria (209,49) | F66: 210,50 > 209,49 > 205,51 > 206,51 > 207,51 | G66: 1 | H66: AM Quatsino | I66: 1 | J66: 0 | K66: AM Quatsino
A67: 323 | B67: Troop transport (?) | C67: (78,171) | D67: (73,163) | E67: (73,163) | F67: 77,171 > 77,170 > 76,169 > 75,169 > 75,168 | G67: 2 | H67: xAP Kaiping | I67: 0.89 | J67: 0 | K67: xAP Kaiping, xAP Minnipa
A68: 324 | B68: Cargo (?) | C68: (226,83) near San Diego | D68: San Diego (227,78) | E68: San Diego (227,78) | F68: 227,82 > 226,81 > 227,80 > 226,79 > 227,78 | G68: 1 | H68: xAK Makawao | I68: 0.68 | J68: 0 | K68: xAK Makawao
A69: 325 | B69: Transport | C69: (29,36) | D69: Aden (20,3) | E69: Aden (20,3) | F69: 28,35 > 29,34 > 29,33 > 29,32 > 29,31 | G69: 7 | H69: TK British Unity | I69: 0.95 | J69: 2 | K69: xAP Largs Bay, xAK African Prince, xAK Bhima, xAK Clan Lamont, xAK Maldive, xAK Michael Embiricos, TK British Unity
A70: 326 | B70: Transport (CS convoy) | C70: (36,5) | D70: Abadan (39,3) | E70: Karachi (40,8) | F70: 37,6 > 38,6 > 38,7 > 39,7 > 40,8 | G70: 2 | H70: xAK Barpeta | I70: 0.41 | J70: 0 | K70: xAK Bandra, xAK Barpeta
A71: 327 | B71: Transport (CS convoy) | C71: (36,5) | D71: Abadan (39,3) | E71: Abadan (39,3) | F71: 37,6 > 38,6 > 38,7 > 39,7 > 40,8 | G71: 1 | H71: xAKL Hermod | I71: 1 | J71: 0 | K71: xAKL Hermod
A72: 328 | B72: Cargo (?) (CS convoy) | C72: (37,5) near Abadan | D72: Abadan (39,3) | E72: Aden (20,3) | F72: 36,5 > 36,5 > 36,5 > 36,5 > 36,5 | G72: 3 | H72: xAK Shinkuang | I72: 1 | J72: 2 | K72: xAKL Louisianan, xAKL Memphis City, xAK Shinkuang
A73: 329 | B73: Transport | C73: (5,20) | D73: Cape Town (2,67) | E73: Cape Town (2,67) | F73: 4,20 > 4,20 > 4,20 > 4,20 > 4,20 | G73: 1 | H73: xAP Chilka | I73: 0.54 | J73: 0 | K73: xAP Chilka
A74: 330 | B74: Transport | C74: (36,5) | D74: Abadan (39,3) | E74: Karachi (40,8) | F74: 37,6 > 38,6 > 38,7 > 39,7 > 40,8 | G74: 8 | H74: AM Bathurst | I74: 1 | J74: 1 | K74: AM Lismore, xAP Indora, xAK El Madina, xAK Jalayamuna, xAK Risaldar, xAK Hatterlock, xAK Borgfred, AM Bathurst
A75: 331 | B75: Transport (CS convoy) | C75: (36,5) | D75: Abadan (39,3) | E75: Perth (49,147) | F75: 37,6 > 36,7 > 36,8 > 35,9 > 35,10 | G75: 18 | H75: TK British Destiny | I75: 1 | J75: 7 | K75: xAP Khedive Ismail, xAK Islami, xAK Ozarda, xAK Pellicula, xAK Shillong, xAK Silverteak, xAK Silverwillow, xAK St Essylt, xAK Itinda, xAK Annalock, xAK Federlock, xAK Alphard, xAK Hermion, xAK Tricolor, xAK Vera, xAK Michael Livanos, TK British Destiny, TK British Aviator
A76: 332 | B76: Transport | C76: (36,6) | D76: Abadan (39,3) | E76: Abadan (39,3) | F76: 35,5 > 35,5 > 35,5 > 35,5 > 35,5 | G76: 7 | H76: xAK Jalapalaka | I76: 1 | J76: 1 | K76: xAKL Dumra, xAK Ho Kiang, xAK Hunan, xAKL Shan Tung, xAKL St. Quentin, xAK Jalapalaka, xAKL Mabella
A77: 333 | B77: Transport | C77: (73,122) near Darwin | D77: Soerabaja (56,104) | E77: Darwin (76,124) | F77: 73,123 > 74,123 > 75,124 > 76,124 > 73,122 | G77: 2 | H77: xAKL Sarangami | I77: 0.73 | J77: 1 | K77: xAKL Sarangami, xAKL Halldor
A78: 336 | B78: Submarine | C78: (54,79) near Bukit Besi | D78: Soerabaja (56,104) | F78: 54,78 > 54,78 > 54,78 > 54,78 > 54,78 | G78: 1 | H78: SS K X | I78: 0.66 | J78: 1 | K78: SS K X
A79: 337 | B79: Transport (CS convoy) | C79: (76,124) Darwin | D79: Sydney (90,167) | E79: Sydney (90,167) | F79: 77,124 > 77,123 > 78,123 > 79,124 > 79,125 | G79: 4 | H79: TK British Judge | I79: 0.76 | J79: 2 | K79: TK Pinna, TK Pleiodon, TK Spirilla, TK British Judge
A80: 338 | B80: Local Minesweeping | C80: (150,144) | D80: near Canton Island (153,143) | E80: near Canton Island (153,143) | F80: 151,144 > 151,143 > 152,143 > 153,143 > 154,142 | G80: 2 | H80: AMc Korowa | I80: 0.71 | J80: 1 | K80: AMc Korowa, AMc Durraween
A81: 339 | B81: Escort (?) | C81: (63,99) near Balikpapan | D81: Soerabaja (56,104) | F81: 63,100 > 62,101 > 62,102 > 61,102 > 60,102 | G81: 1 | H81: CL Java | I81: 1 | J81: 1 | K81: CL Java
A82: 340 | B82: Transport | C82: (47,143) | D82: Perth (49,147) | F82: 48,144 > 48,145 > 49,146 > 49,147 > 48,142 | G82: 7 | H82: xAP Dominion Monarch | I82: 1 | J82: 7 | K82: xAP Dominion Monarch, xAK Demodocus, xAK Neleus, xAK Silverbeech, xAK Tai Sang, xAP Hong Kheng, xAK Zannis Cambanis
A83: 342 | B83: Transport | C83: (4,62) | D83: Cape Town (2,67) | E83: (11,62) | F83: 5,62 > 6,62 > 7,62 > 8,62 > 9,62 | G83: 5 | H83: xAP Aorangi | I83: 0.92 | J83: 0 | K83: xAK Adrastus, xAP Empire Star, xAP Glenartney, xAP Aorangi, xAK Abbekerk
A84: 343 | B84: Cargo (?) | C84: (32,113) | D84: Perth (49,147) | E84: Perth (49,147) | F84: 33,114 > 33,115 > 34,116 > 34,117 > 35,118 | G84: 4 | H84: xAKL Hermelin | I84: 0.35 | J84: 0 | K84: xAKL Chaksang, xAKL Agnes, xAKL Ardent, xAKL Hermelin
A85: 344 | B85: PT patrol (?) | C85: (73,71) Paracel Islands | D85: near Jesselton (66,87) | F85: 74,72 > 73,73 > 74,74 > 73,75 > 73,76 | G85: 1 | H85: MTB MTB 11 | I85: 0 | J85: 1 | K85: MTB MTB 11
A86: 345 | B86: ASW Combat | C86: (186,101) near Lahaina | D86: Pearl Harbor (180,107) | F86: 187,101 > 185,100 > 185,101 > 186,101 > 187,101 | G86: 4 | H86: DD Ralph Talbot | I86: 0.35 | J86: 4 | K86: DD Blue, DD Mugford, DD Ralph Talbot, DD Farragut
A87: 347 | B87: Transport (CS convoy) | C87: (76,118) near Saumlaki | D87: Koepang (68,116) | E87: Koepang (68,116) | F87: 75,117 > 74,117 > 73,117 > 72,117 > 71,117 | G87: 8 | H87: xAKL Mauban | I87: 0.93 | J87: 5 | K87: xAKL Don Jose, xAKL Paz, xAKL Bisayas, xAKL Kanlaon II, xAKL Luzon, xAKL Magallanes, xAKL Mauban, xAKL Montanes
A88: 348 | B88: Transport | C88: (27,6) | D88: Aden (20,3) | E88: Aden (20,3) | F88: 26,5 > 26,5 > 26,5 > 26,5 > 26,5 | G88: 5 | H88: xAK Marion Moller | I88: 0.45 | J88: 1 | K88: xAK Baroda, xAK Hoihow, xAK Hupeh, xAKL Kalarand, xAK Marion Moller
A89: 349 | B89: Transport (CS convoy) | C89: (227,78) San Diego | D89: San Diego (227,78) | E89: Pearl Harbor (180,107) | F89: 226,79 > 225,79 > 225,80 > 224,80 > 223,81 | G89: 2 | H89: xAKL Mapele | I89: 1 | J89: 1 | K89: xAKL Columbian, xAKL Mapele
A90: 350 | B90: Sub special (?) | C90: (204,79) | D90: Pearl Harbor (180,107) | E90: Pearl Harbor (180,107) | F90: 204,80 > 203,80 > 202,81 > 201,81 > 201,82 | G90: 1 | H90: SS Tuna | I90: 0.94 | J90: 0 | K90: SS Tuna
A91: 353 | B91: Submarine | C91: (82,92) near Davao | D91: Darwin (76,124) | F91: 81,93 > 81,93 > 81,93 > 81,93 > 83,94 | G91: 1 | H91: SS Swordfish | I91: 0.83 | J91: 1 | K91: SS Swordfish
A92: 354 | B92: Support (?) | C92: (86,124) | D92: (89,124) | E92: (89,124) | F92: 87,124 > 88,124 > 89,124 > 86,124 > 87,124 | G92: 2 | H92: AVP Heron | I92: 0.72 | J92: 1 | K92: AVP Heron, AVP Fazant
A93: 355 | B93: Transport | C93: (44,43) | D93: Colombo (29,48) | E93: Colombo (29,48) | F93: 44,44 > 43,44 > 42,45 > 41,45 > 41,46 | G93: 1 | H93: xAP Nanchang | I93: 0.88 | J93: 0 | K93: xAP Nanchang
A94: 356 | B94: Cargo (?) | C94: (5,133) | D94: Cape Town (2,67) | E94: Cape Town (2,67) | F94: 4,133 > 4,133 > 4,133 > 4,133 > 4,133 | G94: 1 | H94: xAK Charon | I94: 0.67 | J94: 0 | K94: xAK Charon
A95: 357 | B95: Troop transport (?) | C95: (14,17) | D95: Abadan (39,3) | E95: (16,52) | F95: 15,18 > 14,19 > 15,20 > 14,21 > 15,22 | G95: 5 | H95: AMC Pansy | I95: 0.35 | J95: 3 | K95: xAKL Honolulan, xAKL Oklahoman, xAP Amra, xAK Kiangsu, AMC Pansy
A96: 358 | B96: Transport | C96: (116,167) | D96: San Diego (227,78) | E96: San Diego (227,78) | F96: 117,167 > 118,167 > 119,167 > 120,167 > 121,167 | G96: 2 | H96: AG Steel Worker | I96: 0.92 | J96: 0 | K96: AG Steel Scientist, AG Steel Worker
A97: 359 | B97: Transport | C97: (5,51) | D97: Cape Town (2,67) | E97: Cape Town (2,67) | F97: 4,51 > 4,51 > 4,51 > 4,51 > 4,51 | G97: 1 | H97: xAP Takliwa | I97: 0.68 | J97: 0 | K97: xAP Takliwa
A98: 360 | B98: Cargo (?) | C98: (27,6) | D98: Abadan (39,3) | E98: Abadan (39,3) | F98: 26,5 > 26,5 > 26,5 > 26,5 > 26,5 | G98: 5 | H98: xAK Nord | I98: 0.31 | J98: 2 | K98: xAKL Santa Ana, xAKL Selma City, xAKL Wosang, xAKL Nordhval, xAK Nord
A99: 361 | B99: Transport | C99: (37,5) near Abadan | D99: Abadan (39,3) | E99: Abadan (39,3) | F99: 36,5 > 36,5 > 36,5 > 36,5 > 36,5 | G99: 1 | H99: xAKL Illinoian | I99: 0.92 | J99: 1 | K99: xAKL Illinoian
A100: 362 | B100: Cargo (?) | C100: (37,5) near Abadan | D100: Abadan (39,3) | E100: Abadan (39,3) | F100: 36,5 > 36,5 > 36,5 > 36,5 > 36,5 | G100: 2 | H100: xAK Mundra | I100: 0.96 | J100: 2 | K100: xAK Chilka, xAK Mundra
A101: 363 | B101: Transport (CS convoy) | C101: (36,5) | D101: Abadan (39,3) | E101: Perth (49,147) | F101: 37,6 > 36,7 > 36,8 > 35,9 > 35,10 | G101: 16 | H101: xAK Tanda | I101: 1 | J101: 4 | K101: xAK Alice Moller, xAK Bucegi, xAK Changte, xAK Congella, xAK Gandara, xAK Gogra, xAK Jalaratna, xAK Matiana, xAK Mulbera, xAK Nils Moller, xAK Penrith Castle, xAK Pundit, xAK Singu, xAK Taiping, xAK Tanda, xAK Turing Mary
A102: 364 | B102: Transport | C102: (185,170) | D102: Balboa (229,102) | E102: Balboa (229,102) | F102: 186,170 > 186,169 > 187,169 > 188,169 > 189,169 | G102: 1 | H102: xAK Ellaroo | I102: 0.71 | J102: 1 | K102: xAK Ellaroo
A103: 365 | B103: Transport | C103: (152,139) near Canton Island | D103: San Diego (227,78) | E103: San Diego (227,78) | F103: 153,139 > 154,138 > 155,138 > 155,137 > 156,137 | G103: 5 | H103: xAK Michael Goulandris | I103: 0.67 | J103: 5 | K103: xAK Centaur, xAK Johanne Justesen, xAK Allara, xAK Iron Knob, xAK Michael Goulandris
... A107: 369 | B107: Troop transport (?) | C107: (188,103) | D107: San Diego (227,78) | E107: San Diego (227,78) | F107: 189,103 > 190,102 > 191,102 > 191,101 > 192,101 | G107: 1 | H107: xAKL Regulus | I107: 0.89 | J107: 0 | K107: xAKL Regulus
...

Sheet Damaged Ships
A1: Ship | B1: Type | C1: Class | D1: Nation | E1: Location | F1: TF | G1: Captain | H1: Crew exp | I1: Fuel | J1: Max fuel | K1: Fuel % | L1: Endurance (nm) | M1: Max speed (kn) | N1: Sys dmg | O1: Float dmg | P1: Float major | Q1: Eng dmg | R1: Eng major | S1: Fire
A2: K XV | B2: SS | C2: KXIV Class | D2: Netherlands | E2: At sea, TF 466 (53,91) Tambelan-eilanden | F2: 466 | G2: Kloppman B. | H2: 38 | I2: 130 | J2: 159 | K2: 0.81761006 | L2: 8176 | M2: 17 | N2: 65 | O2: 97 | P2: 20 | Q2: 8 | R2: 2 | S2: 0
A3: Java | B3: CL | C3: Java | D3: Netherlands | E3: At sea, TF 339 (63,99) near Balikpapan | F3: 339 | G3: Vanderhorst E. | H3: 61 | I3: 1200 | J3: 1200 | K3: 1 | L3: 3500 | M3: 31 | N3: 60 | O3: 70 | P3: 30 | Q3: 31 | R3: 7 | S3: 0
A4: California | B4: BB | C4: Tennessee | D4: USA | E4: In port: Pearl Harbor (180,107) | G4: McGuire, Q. | H4: 60 | I4: 4700 | J4: 4900 | K4: 0.95918367 | L4: 9900 | M4: 21 | N4: 27 | O4: 71 | P4: 71 | Q4: 29 | R4: 25 | S4: 0
A5: Tennessee | B5: BB | C5: Tennessee | D5: USA | E5: In port: Pearl Harbor (180,107) | G5: Kennedy, C.B. | H5: 58 | I5: 4700 | J5: 4900 | K5: 0.95918367 | L5: 9900 | M5: 21 | N5: 30 | O5: 70 | P5: 70 | Q5: 19 | R5: 9 | S5: 0
A6: Stuart | B6: DD | C6: Admiralty 'Leader' | D6: Australia | E6: In port: Melbourne (82,170) | G6: Levy, K.M. | H6: 61 | I6: 500 | J6: 500 | K6: 1 | L6: 6250 | M6: 36 | N6: 98 | O6: 0 | P6: 0 | Q6: 90 | R6: 90 | S6: 0
A7: Voyager | B7: DD | C7: Admiralty 'W' | D7: Australia | E7: In port: Sydney (90,167) | G7: Blackwell B. | H7: 62 | I7: 367 | J7: 367 | K7: 1 | L7: 3000 | M7: 34 | N7: 99 | O7: 0 | P7: 0 | Q7: 81 | R7: 81 | S7: 0
A8: West Virginia | B8: BB | C8: West Virginia | D8: USA | E8: At sea, TF 271 (201,92) | F8: 271 | G8: Borowski, W.R. | H8: 53 | I8: 2554 | J8: 5400 | K8: 0.47296296 | L8: 5060 | M8: 21 | N8: 57 | O8: 58 | P8: 44 | Q8: 2 | R8: 0 | S8: 0
A9: Sicard | B9: DM | C9: Clemson DM | D9: USA | E9: In port: Pearl Harbor (180,107) | G9: Fultz, H.L. | H9: 46 | I9: 429 | J9: 435 | K9: 0.9862069 | L9: 5225 | M9: 30 | N9: 86 | O9: 0 | P9: 0 | Q9: 88 | R9: 88 | S9: 0
A10: S-27 | B10: SS | C10: Electric Boat S-18 | D10: USA | E10: In port: Mare Island (218,69) | G10: Jukes, H.L. | H10: 53 | I10: 70 | J10: 70 | K10: 1 | L10: 4050 | M10: 14 | N10: 90 | O10: 0 | P10: 0 | Q10: 71 | R10: 71 | S10: 0
A11: S-28 | B11: SS | C11: Electric Boat S-18 | D11: USA | E11: In port: Mare Island (218,69) | G11: Keene R. | H11: 50 | I11: 70 | J11: 70 | K11: 1 | L11: 4050 | M11: 14 | N11: 90 | O11: 0 | P11: 0 | Q11: 71 | R11: 71 | S11: 0
A12: Capetown | B12: CL | C12: 'C' Class | D12: UK | E12: In port: Bombay (36,24) | G12: Greenwood G. | H12: 73 | I12: 935 | J12: 935 | K12: 1 | L12: 6000 | M12: 29 | N12: 50 | O12: 51 | P12: 51 | Q12: 0 | R12: 0 | S12: 0
A13: Duntroon | B13: xAP | C13: Shire | D13: Australia | E13: At sea, TF 510 (166,159) | F13: 510 | G13: Blackwell W. | H13: 15 | I13: 1241 | J13: 2700 | K13: 0.45962963 | L13: 8273 | M13: 18 | N13: 43 | O13: 34 | P13: 14 | Q13: 12 | R13: 0 | S13: 12
A14: Concord | B14: CL | C14: Omaha | D14: USA | E14: In port: San Diego (227,78) | G14: Birkenbach, R.A. | H14: 55 | I14: 1200 | J14: 1200 | K14: 1 | L14: 9000 | M14: 34 | N14: 75 | O14: 0 | P14: 0 | Q14: 43 | R14: 43 | S14: 0
A15: Limerick | B15: xAP | C15: Dominion Troop | D15: New Zealand | E15: At sea, TF 510 (166,159) | F15: 510 | G15: Usher O. | H15: 17 | I15: 789 | J15: 1505 | K15: 0.52425249 | L15: 7654 | M15: 13 | N15: 45 | O15: 19 | P15: 7 | Q15: 15 | R15: 0 | S15: 14
A16: Nevada | B16: BB | C16: Nevada | D16: USA | E16: At sea, TF 230 (216,70) near San Francisco | F16: 230 | G16: Headrick, O.N. | H16: 55 | I16: 1606 | J16: 3150 | K16: 0.50984127 | L16: 3517 | M16: 21 | N16: 32 | O16: 21 | P16: 21 | Q16: 37 | R16: 29 | S16: 0
A17: Oklahoma | B17: BB | C17: Nevada | D17: USA | E17: At sea, TF 230 (216,70) near San Francisco | F17: 230 | G17: Withers, M.C. | H17: 54 | I17: 1606 | J17: 3150 | K17: 0.50984127 | L17: 3517 | M17: 21 | N17: 42 | O17: 32 | P17: 30 | Q17: 5 | R17: 4 | S17: 0
A18: Repulse | B18: BC | C18: Repulse | D18: UK | E18: At sea, TF 219 (45,106) | F18: 219 | G18: Tennant, W.G. | H18: 74 | I18: 2737 | J18: 3525 | K18: 0.7764539 | L18: 6067 | M18: 28 | N18: 32 | O18: 35 | P18: 35 | Q18: 8 | R18: 3 | S18: 0
A19: Tracy | B19: DM | C19: Clemson DM | D19: USA | E19: In port: Pearl Harbor (180,107) | G19: Gehman, C.T. | H19: 42 | I19: 429 | J19: 435 | K19: 0.9862069 | L19: 5225 | M19: 30 | N19: 85 | O19: 0 | P19: 0 | Q19: 24 | R19: 0 | S19: 0
A20: Preble | B20: DM | C20: Clemson DM | D20: USA | E20: In port: Pearl Harbor (180,107) | G20: Sargent, S.E. | H20: 40 | I20: 429 | J20: 435 | K20: 0.9862069 | L20: 5225 | M20: 30 | N20: 84 | O20: 0 | P20: 0 | Q20: 24 | R20: 0 | S20: 0
A21: Prince of Wales | B21: BB | C21: King George V | D21: UK | E21: At sea, TF 314 (5,102) | F21: 314 | G21: Leach, J.C. | H21: 71 | I21: 2570 | J21: 3850 | K21: 0.66753247 | L21: 4939 | M21: 28 | N21: 10 | O21: 40 | P21: 40 | Q21: 14 | R21: 14 | S21: 0
A22: Arizona | B22: BB | C22: Pennsylvania | D22: USA | E22: At sea, TF 271 (201,92) | F22: 271 | G22: Gruenther, K.S. | H22: 53 | I22: 2116 | J22: 3700 | K22: 0.57189189 | L22: 4632 | M22: 21 | N22: 40 | O22: 22 | P22: 19 | Q22: 14 | R22: 13 | S22: 0
A23: Pruitt | B23: DM | C23: Clemson DM | D23: USA | E23: In port: Pearl Harbor (180,107) | G23: Fenoglia, H. | H23: 50 | I23: 429 | J23: 435 | K23: 0.9862069 | L23: 5225 | M23: 30 | N23: 80 | O23: 0 | P23: 0 | Q23: 7 | R23: 0 | S23: 0
A24: St. Louis | B24: CL | C24: Helena | D24: USA | E24: In port: Mare Island (218,69) | G24: Rood, G. | H24: 56 | I24: 1285 | J24: 1982 | K24: 0.64833502 | L24: 9400 | M24: 32 | N24: 17 | O24: 22 | P24: 22 | Q24: 25 | R24: 25 | S24: 0
A25: Boise | B25: CL | C25: Brooklyn | D25: USA | E25: At sea, TF 300 (63,99) near Balikpapan | F25: 300 | G25: Farley R. | H25: 55 | I25: 1001 | J25: 1982 | K25: 0.50504541 | L25: 7323 | M25: 32 | N25: 24 | O25: 22 | P25: 7 | Q25: 18 | R25: 3 | S25: 0
A26: K VIII | B26: SS | C26: KVIII Class | D26: Netherlands | E26: At sea, TF 459 (52,100) near Bandoeng | F26: 459 | G26: Caspers, J.W. | H26: 58 | I26: 75 | J26: 77 | K26: 0.97402597 | L26: 4821 | M26: 16 | N26: 42 | O26: 15 | P26: 10 | Q26: 2 | R26: 0 | S26: 0
A27: Evertsen | B27: DD | C27: Admiralen Batch I | D27: Netherlands | E27: At sea, TF 300 (63,99) near Balikpapan | F27: 300 | G27: de Vries, W.M. | H27: 57 | I27: 224 | J27: 300 | K27: 0.74666667 | L27: 1866 | M27: 36 | N27: 51 | O27: 5 | P27: 5 | Q27: 11 | R27: 2 | S27: 0
A28: K XI | B28: SS | C28: KXI Class | D28: Netherlands | E28: At sea, TF 461 (34,62) | F28: 461 | G28: Cuyler U. | H28: 56 | I28: 35 | J28: 73 | K28: 0.47945205 | L28: 2301 | M28: 17 | N28: 31 | O28: 20 | P28: 20 | Q28: 0 | R28: 0 | S28: 0
A29: Helena | B29: CL | C29: Helena | D29: USA | E29: In port: near Bremerton (212,52) | G29: Hoover, G. | H29: 58 | I29: 1982 | J29: 1982 | K29: 1 | L29: 14500 | M29: 32 | N29: 13 | O29: 25 | P29: 25 | Q29: 1 | R29: 0 | S29: 0
A30: Shinai | B30: xAKL | C30: Pacific S Cargo | D30: UK | E30: At sea, TF 43 (58,117) | F30: 43 | G30: Woodroffe H. | H30: 15 | I30: 125 | J30: 285 | K30: 0.43859649 | L30: 1754 | M30: 10 | N30: 13 | O30: 24 | P30: 7 | Q30: 0 | R30: 0 | S30: 0
A31: Worden | B31: DD | C31: Farragut | D31: USA | E31: In port: near Bremerton (212,52) | G31: Pogue, W. | H31: 60 | I31: 600 | J31: 600 | K31: 1 | L31: 5750 | M31: 32 | N31: 29 | O31: 8 | P31: 8 | Q31: 15 | R31: 9 | S31: 0
A32: Colorado | B32: BB | C32: Colorado | D32: USA | E32: In port: Bremerton (211,52) | G32: D'Alessio, K.E. | H32: 54 | I32: 4700 | J32: 5400 | K32: 0.87037037 | L32: 10700 | M32: 21 | N32: 39 | O32: 0 | P32: 0 | Q32: 20 | R32: 20 | S32: 0
A33: Tautog | B33: SS | C33: Tambor | D33: USA | E33: In port: Pearl Harbor (180,107) | G33: Willingham, J.H. | H33: 59 | I33: 315 | J33: 315 | K33: 1 | L33: 11000 | M33: 20 | N33: 19 | O33: 16 | P33: 16 | Q33: 6 | R33: 6 | S33: 0
A34: K XIII | B34: SS | C34: KXI Class | D34: Netherlands | E34: At sea, TF 463 (53,80) near Terempa | F34: 463 | G34: Van Den Heuvel W. | H34: 59 | I34: 47 | J34: 73 | K34: 0.64383562 | L34: 3090 | M34: 17 | N34: 27 | O34: 13 | P34: 5 | Q34: 2 | R34: 0 | S34: 0
A35: Mauritius | B35: CL | C35: Fiji | D35: UK | E35: At sea, TF 313 (48,132) | F35: 313 | G35: Stephens, W.D. | H35: 69 | I35: 1236 | J35: 1700 | K35: 0.72705882 | L35: 7997 | M35: 31 | N35: 43 | O35: 0 | P35: 0 | Q35: 0 | R35: 0 | S35: 0
A36: MTB 9 | B36: MTB | C36: BPB 60' MTB | D36: UK | E36: At sea, TF 321 (70,123) | F36: 321 | G36: Trenchard H. | H36: 56 | I36: 12 | J36: 20 | K36: 0.6 | L36: 360 | M36: 33 | N36: 37 | O36: 0 | P36: 0 | Q36: 6 | R36: 2 | S36: 0
A37: Tarpon | B37: SS | C37: Shark | D37: USA | E37: At sea, TF 234 (99,121) | F37: 234 | G37: Wallace, L. | H37: 55 | I37: 191 | J37: 295 | K37: 0.64745763 | L37: 7122 | M37: 19 | N37: 29 | O37: 2 | P37: 0 | Q37: 2 | R37: 0 | S37: 0
A38: Sumatra | B38: CL | C38: Java | D38: Netherlands | E38: In port: Colombo (29,48) | G38: Willinge, J.J.L. | H38: 55 | I38: 1200 | J38: 1200 | K38: 1 | L38: 3500 | M38: 31 | N38: 16 | O38: 0 | P38: 0 | Q38: 17 | R38: 17 | S38: 0
A39: Hanyang | B39: xAK | C39: Pacific M Cargo | D39: UK | E39: At sea, TF 299 (73,122) near Darwin | F39: 299 | G39: Drake B. | H39: 28 | I39: 366 | J39: 447 | K39: 0.81879195 | L39: 4912 | M39: 12 | N39: 24 | O39: 0 | P39: 0 | Q39: 0 | R39: 0 | S39: 0
A40: Peisander | B40: xAK | C40: Dominion L Cargo | D40: UK | E40: At sea, TF 510 (166,159) | F40: 510 | G40: Hackett U. | H40: 24 | I40: 880 | J40: 1700 | K40: 0.51764706 | L40: 8696 | M40: 12 | N40: 12 | O40: 2 | P40: 0 | Q40: 6 | R40: 0 | S40: 0
A41: Dominion Monarch | B41: xAP | C41: Dominion Monarch | D41: UK | E41: At sea, TF 340 (47,143) | F41: 340 | G41: Ross L. | H41: 15 | I41: 2850 | J41: 2850 | K41: 1 | L41: 10100 | M41: 21 | N41: 4 | O41: 0 | P41: 0 | Q41: 16 | R41: 0 | S41: 0
A42: Van Nes | B42: DD | C42: Admiralen Batch II | D42: Netherlands | E42: At sea, TF 419 (57,111) near Denpasar | F42: 419 | G42: Lagay, C.A. | H42: 57 | I42: 261 | J42: 330 | K42: 0.79090909 | L42: 1977 | M42: 36 | N42: 17 | O42: 0 | P42: 0 | Q42: 2 | R42: 1 | S42: 0
A43: Tai Yin | B43: xAK | C43: Euro K Cargo | D43: Other Allied | E43: At sea, TF 510 (166,159) | F43: 510 | G43: Royce D. | H43: 20 | I43: 666 | J43: 1366 | K43: 0.4875549 | L43: 8727 | M43: 14 | N43: 2 | O43: 8 | P43: 3 | Q43: 0 | R43: 0 | S43: 0
A44: Chicago | B44: CA | C44: Northampton | D44: USA | E44: In port: Brisbane (96,160) | G44: Bode, H. | H44: 56 | I44: 2108 | J44: 2108 | K44: 1 | L44: 10500 | M44: 32 | N44: 13 | O44: 0 | P44: 0 | Q44: 4 | R44: 3 | S44: 0
A45: Piet Hein | B45: DD | C45: Admiralen Batch I | D45: Netherlands | E45: At sea, TF 419 (57,111) near Denpasar | F45: 419 | G45: Chompff, J.M.L.I. | H45: 55 | I45: 238 | J45: 300 | K45: 0.79333333 | L45: 1983 | M45: 36 | N45: 12 | O45: 0 | P45: 0 | Q45: 5 | R45: 5 | S45: 0
A46: Encounter | B46: DD | C46: 'E' Class | D46: UK | E46: At sea, TF 313 (48,132) | F46: 313 | G46: Morgan, E.V.St.J. | H46: 70 | I46: 141 | J46: 380 | K46: 0.37105263 | L46: 1762 | M46: 35 | N46: 17 | O46: 0 | P46: 0 | Q46: 0 | R46: 0 | S46: 0
A47: De Ruyter | B47: CL | C47: De Ruyter | D47: Netherlands | E47: At sea, TF 419 (57,111) near Denpasar | F47: 419 | G47: Kuipers F. | H47: 59 | I47: 1141 | J47: 1300 | K47: 0.87769231 | L47: 3730 | M47: 33 | N47: 13 | O47: 0 | P47: 0 | Q47: 2 | R47: 2 | S47: 0
A48: Witte de With | B48: DD | C48: Admiralen Batch II | D48: Netherlands | E48: At sea, TF 419 (57,111) near Denpasar | F48: 419 | G48: Schotel, P. | H48: 61 | I48: 261 | J48: 330 | K48: 0.79090909 | L48: 1977 | M48: 36 | N48: 12 | O48: 0 | P48: 0 | Q48: 3 | R48: 3 | S48: 0
A49: Lexington | B49: CV | C49: Lexington | D49: USA | E49: In port: Brisbane (96,160) | G49: Sherman, Frederick | H49: 55 | I49: 3759 | J49: 5432 | K49: 0.69201031 | L49: 6920 | M49: 33 | N49: 12 | O49: 0 | P49: 0 | Q49: 2 | R49: 2 | S49: 0
A50: Drayton | B50: DD | C50: Mahan | D50: USA | E50: In port: Brisbane (96,160) | G50: Cooper, J. | H50: 59 | I50: 522 | J50: 522 | K50: 1 | L50: 6500 | M50: 35 | N50: 12 | O50: 0 | P50: 0 | Q50: 2 | R50: 1 | S50: 0
A51: Scout | B51: DD | C51: Admiralty 'S' | D51: UK | E51: In port: Darwin (76,124) | G51: Lambton, H. | H51: 73 | I51: 199 | J51: 301 | K51: 0.66112957 | L51: 2809 | M51: 36 | N51: 11 | O51: 0 | P51: 0 | Q51: 3 | R51: 3 | S51: 0
A52: Sealion | B52: SS | C52: Seadragon | D52: USA | E52: At sea, TF 411 (147,107) | F52: 411 | G52: Friedrichsen, G.V. | H52: 58 | I52: 212 | J52: 314 | K52: 0.67515924 | L52: 7426 | M52: 21 | N52: 14 | O52: 0 | P52: 0 | Q52: 0 | R52: 0 | S52: 0
A53: MTB 26 | B53: MTB | C53: BPB 60' MTB | D53: UK | E53: At sea, TF 321 (70,123) | F53: 321 | G53: Gilmour L. | H53: 48 | I53: 12 | J53: 20 | K53: 0.6 | L53: 360 | M53: 33 | N53: 13 | O53: 0 | P53: 0 | Q53: 1 | R53: 1 | S53: 0
A54: Maury | B54: DD | C54: Gridley | D54: USA | E54: In port: Brisbane (96,160) | G54: Sims, G. | H54: 60 | I54: 525 | J54: 525 | K54: 1 | L54: 8000 | M54: 35 | N54: 10 | O54: 0 | P54: 0 | Q54: 3 | R54: 3 | S54: 0
A55: Isis | B55: DD | C55: 'I' Class | D55: UK | E55: At sea, TF 313 (48,132) | F55: 313 | G55: Swinley, C.S.B. | H55: 74 | I55: 141 | J55: 380 | K55: 0.37105263 | L55: 1762 | M55: 35 | N55: 13 | O55: 0 | P55: 0 | Q55: 0 | R55: 0 | S55: 0
A56: Banckert | B56: DD | C56: Admiralen Batch II | D56: Netherlands | E56: At sea, TF 419 (57,111) near Denpasar | F56: 419 | G56: Goslings, L.J. | H56: 56 | I56: 261 | J56: 330 | K56: 0.79090909 | L56: 1977 | M56: 36 | N56: 9 | O56: 0 | P56: 0 | Q56: 3 | R56: 3 | S56: 0
A57: PT-34 | B57: PT | C57: Elco 77ft PT | D57: USA | E57: At sea, TF 424 (77,117) near Saumlaki | F57: 424 | G57: Berg, F.A. | H57: 44 | I57: 9 | J57: 16 | K57: 0.5625 | L57: 281 | M57: 39 | N57: 10 | O57: 0 | P57: 0 | Q57: 2 | R57: 0 | S57: 0
A58: Chilka | B58: xAK | C58: Pacific L Cargo | D58: UK | E58: At sea, TF 362 (37,5) near Abadan | F58: 362 | G58: Middelton O. | H58: 24 | I58: 1265 | J58: 1320 | K58: 0.95833333 | L58: 11498 | M58: 12 | N58: 12 | O58: 0 | P58: 0 | Q58: 0 | R58: 0 | S58: 0
A59: MTB 7 | B59: MTB | C59: BPB 60' MTB | D59: UK | E59: At sea, TF 321 (70,123) | F59: 321 | G59: Trent F. | H59: 47 | I59: 12 | J59: 20 | K59: 0.6 | L59: 360 | M59: 33 | N59: 8 | O59: 0 | P59: 0 | Q59: 4 | R59: 2 | S59: 0
A60: Porter | B60: DD | C60: Porter | D60: USA | E60: In port: Brisbane (96,160) | G60: Roberts, D. | H60: 59 | I60: 635 | J60: 635 | K60: 1 | L60: 7500 | M60: 34 | N60: 10 | O60: 0 | P60: 0 | Q60: 1 | R60: 0 | S60: 0
A61: Peary | B61: APD | C61: Clemson APD | D61: USA | E61: In port: Colombo (29,48) | G61: Webster, V.W. | H61: 57 | I61: 385 | J61: 385 | K61: 1 | L61: 4625 | M61: 27 | N61: 11 | O61: 0 | P61: 0 | Q61: 0 | R61: 0 | S61: 0
A62: Portland | B62: CA | C62: Portland | D62: USA | E62: In port: Brisbane (96,160) | G62: Perlman, B. | H62: 55 | I62: 2125 | J62: 2125 | K62: 1 | L62: 10500 | M62: 32 | N62: 8 | O62: 0 | P62: 0 | Q62: 2 | R62: 1 | S62: 0
A63: Chester | B63: CA | C63: Northampton | D63: USA | E63: In port: Brisbane (96,160) | G63: Shock, T. | H63: 61 | I63: 2059 | J63: 2108 | K63: 0.97675522 | L63: 10255 | M63: 32 | N63: 7 | O63: 0 | P63: 0 | Q63: 3 | R63: 3 | S63: 0
A64: Marblehead | B64: CL | C64: Omaha | D64: USA | E64: At sea, TF 321 (70,123) | F64: 321 | G64: Short O. | H64: 60 | I64: 1035 | J64: 1200 | K64: 0.8625 | L64: 7762 | M64: 34 | N64: 9 | O64: 0 | P64: 0 | Q64: 1 | R64: 0 | S64: 0
A65: Barker | B65: APD | C65: Clemson APD | D65: USA | E65: In port: Brisbane (96,160) | G65: Abbate, E.O. | H65: 61 | I65: 385 | J65: 385 | K65: 1 | L65: 4625 | M65: 27 | N65: 10 | O65: 0 | P65: 0 | Q65: 0 | R65: 0 | S65: 0
A66: Stewart | B66: APD | C66: Clemson APD | D66: USA | E66: In port: Brisbane (96,160) | G66: Glass A. | H66: 56 | I66: 385 | J66: 385 | K66: 1 | L66: 4625 | M66: 27 | N66: 10 | O66: 0 | P66: 0 | Q66: 0 | R66: 0 | S66: 0
A67: K XIV | B67: SS | C67: KXIV Class | D67: Netherlands | E67: At sea, TF 465 (53,81) Terempa | F67: 465 | G67: Kuipers A. | H67: 57 | I67: 121 | J67: 159 | K67: 0.76100629 | L67: 7610 | M67: 17 | N67: 10 | O67: 0 | P67: 0 | Q67: 0 | R67: 0 | S67: 0
A68: MTB 11 | B68: MTB | C68: BPB 60' MTB | D68: UK | E68: At sea, TF 344 (73,71) Paracel Islands | F68: 344 | G68: Gilmour J. | H68: 49 | I68: 0 | J68: 20 | K68: 0 | L68: 0 | M68: 33 | N68: 8 | O68: 0 | P68: 0 | Q68: 2 | R68: 1 | S68: 0
A69: Gridley | B69: DD | C69: Gridley | D69: USA | E69: In port: Brisbane (96,160) | G69: Stickney, F. | H69: 61 | I69: 525 | J69: 525 | K69: 1 | L69: 8000 | M69: 35 | N69: 7 | O69: 0 | P69: 0 | Q69: 2 | R69: 1 | S69: 0
A70: Parrott | B70: APD | C70: Clemson APD | D70: USA | E70: In port: Brisbane (96,160) | G70: Kachinsky, O.W. | H70: 59 | I70: 385 | J70: 385 | K70: 1 | L70: 4625 | M70: 27 | N70: 9 | O70: 0 | P70: 0 | Q70: 0 | R70: 0 | S70: 0
A71: Seadragon | B71: SS | C71: Seadragon | D71: USA | E71: At sea, TF 411 (147,107) | F71: 411 | G71: Ferrall, W.E. | H71: 54 | I71: 212 | J71: 314 | K71: 0.67515924 | L71: 7426 | M71: 21 | N71: 9 | O71: 0 | P71: 0 | Q71: 0 | R71: 0 | S71: 0
A72: Swan | B72: PG | C72: Swan | D72: Australia | E72: In port: Townsville (92,144) | G72: Badham, D.V. | H72: 39 | I72: 317 | J72: 317 | K72: 1 | L72: 4500 | M72: 16 | N72: 9 | O72: 0 | P72: 0 | Q72: 0 | R72: 0 | S72: 0
A73: MTB 27 | B73: MTB | C73: BPB 60' MTB | D73: UK | E73: At sea, TF 321 (70,123) | F73: 321 | G73: Murray M. | H73: 50 | I73: 12 | J73: 20 | K73: 0.6 | L73: 360 | M73: 33 | N73: 8 | O73: 0 | P73: 0 | Q73: 1 | R73: 0 | S73: 0
A74: Northampton | B74: CA | C74: Northampton | D74: USA | E74: In port: Brisbane (96,160) | G74: Chandler, W. | H74: 55 | I74: 2108 | J74: 2108 | K74: 1 | L74: 10500 | M74: 32 | N74: 6 | O74: 0 | P74: 0 | Q74: 2 | R74: 1 | S74: 0
A75: Salt Lake City | B75: CA | C75: Pensacola | D75: USA | E75: In port: Brisbane (96,160) | G75: Small, E. | H75: 55 | I75: 2115 | J75: 2116 | K75: 0.99952741 | L75: 10495 | M75: 32 | N75: 6 | O75: 0 | P75: 0 | Q75: 2 | R75: 2 | S75: 0
A76: Astoria | B76: CA | C76: New Orleans | D76: USA | E76: In port: Brisbane (96,160) | G76: Scanland, F. | H76: 55 | I76: 1860 | J76: 1861 | K76: 0.99946265 | L76: 9994 | M76: 32 | N76: 6 | O76: 0 | P76: 0 | Q76: 2 | R76: 2 | S76: 0
A77: Trenton | B77: CL | C77: Omaha | D77: USA | E77: At sea, TF 242 (139,170) | F77: 242 | G77: Simmons N. | H77: 55 | I77: 408 | J77: 1200 | K77: 0.34 | L77: 3060 | M77: 34 | N77: 4 | O77: 0 | P77: 0 | Q77: 4 | R77: 0 | S77: 0
A78: Balch | B78: DD | C78: Porter | D78: USA | E78: In port: Brisbane (96,160) | G78: Tiemroth, H. | H78: 61 | I78: 635 | J78: 635 | K78: 1 | L78: 7500 | M78: 34 | N78: 5 | O78: 0 | P78: 0 | Q78: 3 | R78: 2 | S78: 0
A79: Paul Jones | B79: APD | C79: Clemson APD | D79: USA | E79: In port: Brisbane (96,160) | G79: Gawron, L.G. | H79: 55 | I79: 385 | J79: 385 | K79: 1 | L79: 4625 | M79: 27 | N79: 8 | O79: 0 | P79: 0 | Q79: 0 | R79: 0 | S79: 0
A80: Blue | B80: DD | C80: Bagley | D80: USA | E80: At sea, TF 345 (186,101) near Lahaina | F80: 345 | G80: Williams, H. | H80: 57 | I80: 281 | J80: 525 | K80: 0.5352381 | L80: 4281 | M80: 35 | N80: 4 | O80: 0 | P80: 0 | Q80: 3 | R80: 2 | S80: 0
A81: Mahan | B81: DD | C81: Mahan | D81: USA | E81: In port: Brisbane (96,160) | G81: Simpson, Rodger W. | H81: 56 | I81: 522 | J81: 522 | K81: 1 | L81: 6500 | M81: 35 | N81: 6 | O81: 0 | P81: 0 | Q81: 1 | R81: 1 | S81: 0
A82: Neleus | B82: xAK | C82: Dominion M Cargo | D82: UK | E82: At sea, TF 340 (47,143) | F82: 340 | G82: Ricketts L. | H82: 15 | I82: 1505 | J82: 1505 | K82: 1 | L82: 14600 | M82: 13 | N82: 4 | O82: 0 | P82: 0 | Q82: 3 | R82: 0 | S82: 0
A83: Fanning | B83: DD | C83: Fanning | D83: USA | E83: In port: Brisbane (96,160) | G83: Imes, E. | H83: 55 | I83: 522 | J83: 522 | K83: 1 | L83: 6500 | M83: 35 | N83: 5 | O83: 0 | P83: 0 | Q83: 1 | R83: 1 | S83: 0
A84: K X | B84: SS | C84: KVIII Class | D84: Netherlands | E84: At sea, TF 336 (54,79) near Bukit Besi | F84: 336 | G84: de Back, P.G. | H84: 57 | I84: 51 | J84: 77 | K84: 0.66233766 | L84: 3278 | M84: 16 | N84: 6 | O84: 0 | P84: 0 | Q84: 0 | R84: 0 | S84: 0
A85: PT-31 | B85: PT | C85: Elco 77ft PT | D85: USA | E85: In port: Darwin (76,124) | G85: Piwonski, C.G. | H85: 50 | I85: 16 | J85: 16 | K85: 1 | L85: 500 | M85: 39 | N85: 6 | O85: 0 | P85: 0 | Q85: 0 | R85: 0 | S85: 0
A86: Ethel Edwards | B86: xAK | C86: Harriman Cargo | D86: USA | E86: At sea, TF 543 (76,124) Darwin | F86: 543 | G86: Eyster, E.S. | H86: 23 | I86: 1450 | J86: 1450 | K86: 1 | L86: 14900 | M86: 12 | N86: 4 | O86: 0 | P86: 0 | Q86: 2 | R86: 0 | S86: 0
A87: Warrego | B87: PG | C87: Warrego | D87: Australia | E87: In port: Townsville (92,144) | G87: McShane, L.N. | H87: 37 | I87: 317 | J87: 317 | K87: 1 | L87: 4500 | M87: 16 | N87: 6 | O87: 0 | P87: 0 | Q87: 0 | R87: 0 | S87: 0
A88: Momba | B88: xAK | C88: Pacific M Cargo | D88: Australia | E88: At sea, TF 294 (120,150) Luganville | F88: 294 | G88: Shannon I. | H88: 15 | I88: 243 | J88: 447 | K88: 0.54362416 | L88: 3261 | M88: 12 | N88: 3 | O88: 0 | P88: 0 | Q88: 3 | R88: 0 | S88: 0
A89: British Motorist | B89: TK | C89: Federal Type-E | D89: UK | E89: At sea, TF 18 (48,128) | F89: 18 | G89: Campbell G. | H89: 25 | I89: 1240 | J89: 1321 | K89: 0.93868282 | L89: 11264 | M89: 14 | N89: 5 | O89: 0 | P89: 0 | Q89: 1 | R89: 1 | S89: 0
A90: Enterprise | B90: CV | C90: Yorktown | D90: USA | E90: In port: Brisbane (96,160) | G90: Murray, G.D. | H90: 52 | I90: 4360 | J90: 4360 | K90: 1 | L90: 12000 | M90: 32 | N90: 4 | O90: 0 | P90: 0 | Q90: 1 | R90: 1 | S90: 0
A91: Houston | B91: CA | C91: Northampton | D91: USA | E91: At sea, TF 321 (70,123) | F91: 321 | G91: Riker, K.I. | H91: 55 | I91: 1780 | J91: 2108 | K91: 0.84440228 | L91: 8866 | M91: 32 | N91: 5 | O91: 0 | P91: 0 | Q91: 0 | R91: 0 | S91: 0
A92: Morris | B92: DD | C92: Sims | D92: USA | E92: At sea, TF 548 (226,107) | F92: 548 | G92: King P. | H92: 42 | I92: 30 | J92: 459 | K92: 0.065359477 | L92: 408 | M92: 35 | N92: 5 | O92: 0 | P92: 0 | Q92: 0 | R92: 0 | S92: 0
A93: Craven | B93: DD | C93: Gridley | D93: USA | E93: In port: Brisbane (96,160) | G93: Puglia, R.O. | H93: 57 | I93: 525 | J93: 525 | K93: 1 | L93: 8000 | M93: 35 | N93: 3 | O93: 0 | P93: 0 | Q93: 2 | R93: 2 | S93: 0
A94: Langley | B94: AV | C94: Langley | D94: USA | E94: In port: Darwin (76,124) | G94: Scott N. | H94: 24 | I94: 940 | J94: 940 | K94: 1 | L94: 8800 | M94: 15 | N94: 5 | O94: 0 | P94: 0 | Q94: 0 | R94: 0 | S94: 0
A95: S-41 | B95: SS | C95: Electric Boat S-18 | D95: USA | E95: At sea, TF 256 (74,123) near Darwin | F95: 256 | G95: Holley, G.M. | H95: 54 | I95: 11 | J95: 70 | K95: 0.15714286 | L95: 636 | M95: 14 | N95: 4 | O95: 0 | P95: 0 | Q95: 1 | R95: 0 | S95: 0
A96: PT-32 | B96: PT | C96: Elco 77ft PT | D96: USA | E96: At sea, TF 424 (77,117) near Saumlaki | F96: 424 | G96: Landers, F.T. | H96: 50 | I96: 9 | J96: 16 | K96: 0.5625 | L96: 281 | M96: 39 | N96: 5 | O96: 0 | P96: 0 | Q96: 0 | R96: 0 | S96: 0
A97: PT-35 | B97: PT | C97: Elco 77ft PT | D97: USA | E97: In port: Darwin (76,124) | G97: Zubal, D.G. | H97: 46 | I97: 16 | J97: 16 | K97: 1 | L97: 500 | M97: 39 | N97: 5 | O97: 0 | P97: 0 | Q97: 0 | R97: 0 | S97: 0
A98: Paz | B98: xAKL | C98: Coastal Cargo | D98: Philippines | E98: At sea, TF 347 (76,118) near Saumlaki | F98: 347 | G98: Balboa O. | H98: 17 | I98: 207 | J98: 221 | K98: 0.93665158 | L98: 3746 | M98: 10 | N98: 4 | O98: 0 | P98: 0 | Q98: 1 | R98: 1 | S98: 0
A99: Coast Farmer | B99: xAK | C99: Hog Island Cargo | D99: USA | E99: At sea, TF 488 (120,150) Luganville | F99: 488 | G99: Caprio, L.P. | H99: 23 | I99: 201 | J99: 1440 | K99: 0.13958333 | L99: 2051 | M99: 12 | N99: 3 | O99: 0 | P99: 0 | Q99: 2 | R99: 0 | S99: 0
A100: Palawan | B100: xAKL | C100: Pacific S Cargo | D100: Philippines | E100: At sea, TF 496 (61,124) | F100: 496 | G100: Bayo E. | H100: 16 | I100: 285 | J100: 285 | K100: 1 | L100: 4000 | M100: 10 | N100: 3 | O100: 0 | P100: 0 | Q100: 2 | R100: 0 | S100: 0
...

Sheet Losses
A1: Ship | B1: Type | C1: Class | D1: Nation | E1: Lost | F1: Last captain
A2: Manoora | B2: AMC | C2: Manoora AMC | D2: Australia | E2: on or before 17 Dec
A3: Platte | B3: AO | C3: Neosho | D3: USA | E3: on or before 17 Dec | F3: Henkle, R.
A4: William B. Preston | B4: AVD | C4: Clemson AVD | D4: USA | E4: on or before 17 Dec
A5: Maryland | B5: BB | C5: Maryland | D5: USA | E5: on or before 17 Dec | F5: Badger, B.W.
A6: Tromp | B6: CL | C6: Tromp | D6: Netherlands | E6: on or before 17 Dec
A7: John D. Ford | B7: DD | C7: Clemson DD | D7: USA | E7: on or before 17 Dec
A8: Pillsbury | B8: DD | C8: Clemson DD | D8: USA | E8: on or before 17 Dec
A9: Pope | B9: DD | C9: Clemson DD | D9: USA | E9: on or before 17 Dec | F9: Musak, F.V.
A10: Kortenaer | B10: DD | C10: Admiralen Batch I | D10: Netherlands | E10: on or before 17 Dec | F10: Kroese, A.
A11: HDML 1062 | B11: HDML | C11: Admiralty HDML | D11: UK | E11: on or before 17 Dec | F11: Sparks T.
A12: HDML 1063 | B12: HDML | C12: Admiralty HDML | D12: UK | E12: on or before 17 Dec | F12: Pringle U.
A13: Pro Patria | B13: ML | C13: Pro Patria | D13: Netherlands | E13: on or before 17 Dec | F13: Haerlen W.
A14: No. 376 | B14: ML | C14: Fairmile B | D14: UK | E14: on or before 17 Dec | F14: Underwood E.
A15: No. 377 | B15: ML | C15: Fairmile B | D15: UK | E15: on or before 17 Dec | F15: Trent F.
A16: Reliance | B16: PC | C16: Active 125' PC | D16: USA | E16: on or before 17 Dec
A17: Governor Wright | B17: xAK | C17: Harriman Cargo | D17: USA | E17: on or before 17 Dec
A18: Bennevis | B18: xAK | C18: Dominion L Cargo | D18: UK | E18: on or before 17 Dec
A19: Demosthenes | B19: xAK | C19: Dominion M Cargo | D19: UK | E19: on or before 17 Dec
A20: Ellenga | B20: xAK | C20: Pacific L Cargo | D20: UK | E20: on or before 17 Dec
A21: Fatshan | B21: xAK | C21: Pacific M Cargo | D21: UK | E21: on or before 17 Dec | F21: Kershaw R.
A22: Indira | B22: xAK | C22: Euro M Cargo | D22: UK | E22: on or before 17 Dec | F22: Peirse N.
A23: Ming Sang | B23: xAK | C23: Pacific L Cargo | D23: UK | E23: on or before 17 Dec | F23: Elster F.
A24: Wing Sang | B24: xAK | C24: Pacific L Cargo | D24: UK | E24: on or before 17 Dec
A25: Lorraine | B25: xAK | C25: Pacific M Cargo | D25: Free French | E25: on or before 17 Dec | F25: Beaufre R.
A26: Somelsdijk | B26: xAK | C26: Euro L Cargo | D26: Netherlands | E26: on or before 17 Dec | F26: Nieuwhuis T.
A27: Toendjoek | B27: xAK | C27: Euro K Cargo | D27: Netherlands | E27: on or before 17 Dec | F27: Balluseck U.
A28: Haraldsvang | B28: xAK | C28: Pacific M Cargo | D28: Other Allied | E28: on or before 17 Dec | F28: Kent U.
A29: Susana | B29: xAKL | C29: Lake Cargo | D29: USA | E29: on or before 17 Dec | F29: Rowan, P.H.
A30: Manini | B30: xAKL | C30: Lake Cargo | D30: USA | E30: on or before 17 Dec
A31: Latouche | B31: xAKL | C31: Coastal Cargo | D31: Philippines | E31: on or before 17 Dec
A32: Legazpi | B32: xAKL | C32: Pacific S Cargo | D32: Philippines | E32: on or before 17 Dec | F32: Echegaray U.
A33: Lepus | B33: xAKL | C33: Coastal Cargo | D33: Philippines | E33: on or before 17 Dec
A34: Surigao | B34: xAKL | C34: Coastal Cargo | D34: Philippines | E34: on or before 17 Dec
A35: Joan Moller | B35: xAKL | C35: Pacific S Cargo | D35: UK | E35: on or before 17 Dec
A36: Lyemun | B36: xAKL | C36: Pacific S Cargo | D36: UK | E36: on or before 17 Dec | F36: Gifford W.
A37: Nam Yong | B37: xAKL | C37: Coastal Cargo | D37: UK | E37: on or before 17 Dec
A38: Yat Shing | B38: xAKL | C38: Pacific S Cargo | D38: UK | E38: on or before 17 Dec
A39: Glenapp | B39: xAP | C39: Empire/Glen | D39: UK | E39: on or before 17 Dec | F39: Caruthers C.
A40: Hong Siang | B40: xAP | C40: Straits/Hong | D40: UK | E40: on or before 17 Dec
A41: Sin Kheng Seng | B41: xAP | C41: Straits/Matang | D41: UK | E41: on or before 17 Dec | F41: Baldwin B.
A42: Kedah | B42: xAP | C42: Straits/Kedah | D42: Other Allied | E42: on or before 17 Dec
A43: Kelantan | B43: xAP | C43: Straits/Kedah | D43: Other Allied | E43: on or before 17 Dec
A44: Barossa | B44: xAK | C44: Euro M Cargo | D44: Australia | E44: 17 Dec turn
A45: Dundula | B45: xAK | C45: Pacific L Cargo | D45: Australia | E45: 17 Dec turn
A46: Mary Livanos | B46: xAK | C46: Euro M Cargo | D46: Other Allied | E46: 17 Dec turn
A47: Chengtu | B47: xAKL | C47: Pacific S Cargo | D47: UK | E47: 17 Dec turn | F47: Higgins N.
A48: Marudu | B48: xAKL | C48: Pacific S Cargo | D48: UK | E48: 17 Dec turn | F48: Lake C.
A49: Bust | B49: xAKL | C49: Coastal Cargo | D49: Other Allied | E49: 17 Dec turn | F49: Munro E.
A50: Kepong | B50: xAP | C50: Straits/Matang | D50: Other Allied | E50: 17 Dec turn
A51: Rangitata | B51: xAP | C51: Rangi/Bay | D51: Australia | E51: 17 Dec turn
A52: No. 310 | B52: ML | C52: Fairmile B | D52: UK | E52: 18 Dec turn
A53: No. 311 | B53: ML | C53: Fairmile B | D53: UK | E53: 18 Dec turn
A54: Gulfpride | B54: TK | C54: Esso Type-T | D54: USA | E54: 18 Dec turn
A55: Si Kiang | B55: xAK | C55: Dominion M Cargo | D55: USA | E55: 18 Dec turn | F55: Terry, M.J.
A56: Wulin | B56: xAK | C56: Pacific M Cargo | D56: UK | E56: 18 Dec turn | F56: Goodwin J.
A57: Ipoh | B57: xAKL | C57: Coastal Cargo | D57: UK | E57: 18 Dec turn
A58: Tatung | B58: xAKL | C58: Pacific S Cargo | D58: UK | E58: 18 Dec turn
A59: Matang | B59: xAP | C59: Straits/Matang | D59: Other Allied | E59: 18 Dec turn
A60: Pennsylvania | B60: BB | C60: Pennsylvania | D60: USA | E60: 19 Dec turn | F60: Hanley, T.H.
A61: Van Ghent | B61: DD | C61: Admiralen Batch I | D61: Netherlands | E61: 19 Dec turn
A62: MTB 8 | B62: MTB | C62: BPB 60' MTB | D62: UK | E62: 19 Dec turn | F62: Greenwell G.
A63: MTB 10 | B63: MTB | C63: BPB 60' MTB | D63: UK | E63: 19 Dec turn
A64: MTB 12 | B64: MTB | C64: BPB 60' MTB | D64: UK | E64: 19 Dec turn | F64: Snowdon K.
A65: Eidsvold | B65: TK | C65: ETC Type-M | D65: Other Allied | E65: 19 Dec turn | F65: Rankin M.
A66: Capillo | B66: xAK | C66: Isthmian Cargo | D66: USA | E66: 19 Dec turn
A67: Soochow | B67: xAKL | C67: Pacific S Cargo | D67: UK | E67: 19 Dec turn
A68: Bellatrix | B68: AVP | C68: Sm.Gouv.Mar. AVP | D68: Netherlands | E68: 20 Dec turn | F68: Frelinghuysen V.
A69: Reiger | B69: AVP | C69: Sm.Gouv.Mar. AVP | D69: Netherlands | E69: 20 Dec turn | F69: Balluseck D.
A70: Herald | B70: PG | C70: WWI '24' Class | D70: UK | E70: 20 Dec turn
A71: K XVII | B71: SS | C71: KXIV Class | D71: Netherlands | E71: 20 Dec turn | F71: Michaelius D.
A72: Ngakuta | B72: xAKL | C72: Coastal Cargo | D72: UK | E72: 20 Dec turn | F72: Fisher M.
A73: Wear | B73: xAKL | C73: Coastal Cargo | D73: UK | E73: 20 Dec turn
A74: Hetton Bank | B74: xAKL | C74: Coastal Cargo | D74: Australia | E74: 20 Dec turn | F74: Kilgore H.
A75: Koonda | B75: xAKL | C75: Coastal Cargo | D75: Australia | E75: 20 Dec turn
A76: Kota Tjandi | B76: xAP | C76: Kota Troop | D76: Netherlands | E76: 21 Dec turn
A77: Samuel Benbow | B77: AMc | C77: Castle Trawler | D77: Australia | E77: 22 Dec turn | F77: Greenwood M.
A78: Goolgwai | B78: AMc | C78: Castle Trawler | D78: Australia | E78: 22 Dec turn
A79: Goonambee | B79: AMc | C79: Castle Trawler | D79: Australia | E79: 22 Dec turn | F79: Davies R.
A80: Adelaide | B80: CL | C80: Birmingham | D80: Australia | E80: 22 Dec turn | F80: Showers, H.A.
A81: Vendetta | B81: DD | C81: Admiralty 'V' | D81: Australia | E81: 22 Dec turn | F81: Hager, J.H.
A82: Le Triomphant | B82: DD | C82: Le Fantasque | D82: Free French | E82: 22 Dec turn
A83: Sunchaser | B83: TK | C83: Sun Type-H | D83: USA | E83: 22 Dec turn
A84: Elisavet | B84: xAK | C84: Pacific M Cargo | D84: Other Allied | E84: 22 Dec turn | F84: Edge F.
A85: Steel Mariner | B85: AG | C85: Isthmian Tender | D85: USA | E85: 23 Dec turn | F85: Stockna, E.L.
A86: Danae | B86: CL | C86: 'D' Class | D86: UK | E86: 23 Dec turn
A87: Hinsang | B87: xAK | C87: Euro M Cargo | D87: UK | E87: 23 Dec turn | F87: Downey F.
A88: Argus | B88: xAKL | C88: Coastal Cargo | D88: Other Allied | E88: 23 Dec turn
A89: Woolgar | B89: xAK | C89: Pacific M Cargo | D89: Other Allied | E89: 24 Dec turn | F89: Walker M.
A90: Soerabaja | B90: xAKL | C90: Coastal Cargo | D90: Netherlands | E90: 24 Dec turn | F90: Unverdorben L.
A91: Parigi | B91: xAKL | C91: Coastal Cargo | D91: Netherlands | E91: 24 Dec turn | F91: Cortlandt B.
A92: Siberoet | B92: xAKL | C92: Coastal Cargo | D92: Netherlands | E92: 24 Dec turn | F92: Heidkamp M.
A93: Prominent | B93: xAKL | C93: Pacific S Cargo | D93: Other Allied | E93: 24 Dec turn
A94: Pijnacker Hordijk | B94: xAP | C94: KPM Troop | D94: Netherlands | E94: 24 Dec turn | F94: Reiger F.

Sheet Reinforcements
A1: Ship | B1: Type | C1: Class | D1: Nation | E1: Days to arrival | F1: Arrival date | G1: Arrives at
A2: Alchiba | B2: AK | C2: C2 Arcturus | D2: USA | E2: 1 | F2: 1941-12-26 | G2: (227,27)
A3: Strela | B3: AM | C3: Fugas | D3: nation 13 | E3: 1 | F3: 1941-12-26 | G3: near Yenki (112,46)
A4: Cheka | B4: AM | C4: Fugas | D4: nation 13 | E4: 1 | F4: 1941-12-26 | G4: near Yenki (112,46)
A5: Tros | B5: AM | C5: Fugas | D5: nation 13 | E5: 1 | F5: 1941-12-26 | G5: (126,37)
A6: Provodnik | B6: AM | C6: Fugas | D6: nation 13 | E6: 1 | F6: 1941-12-26 | G6: (126,37)
A7: Podsekate | B7: AM | C7: Fugas | D7: nation 13 | E7: 1 | F7: 1941-12-26 | G7: near Yenki (112,46)
A8: Vekha | B8: AM | C8: Fugas | D8: nation 13 | E8: 1 | F8: 1941-12-26 | G8: near Yenki (112,46)
A9: Kapsul | B9: AM | C9: Fugas | D9: nation 13 | E9: 1 | F9: 1941-12-26 | G9: (124,42)
A10: Emerald | B10: CL | C10: 'E' Class 1st Group | D10: UK | E10: 1 | F10: 1941-12-26 | G10: (2,57)
A11: Tbilisi | B11: DD | C11: Leningrad | D11: nation 13 | E11: 1 | F11: 1941-12-26 | G11: near Yenki (112,46)
A12: Ryanyj | B12: DD | C12: Gnevnyi | D12: nation 13 | E12: 1 | F12: 1941-12-26 | G12: near Yenki (112,46)
A13: Rastoropnyj | B13: DD | C13: Gnevnyi | D13: nation 13 | E13: 1 | F13: 1941-12-26 | G13: near Yenki (112,46)
... A364: Uffington Court | B364: xAK | C364: Euro M Cargo | D364: UK | E364: 64 | F364: 1942-02-27 | G364: Aden (20,3)
A365: PT-61 | B365: PT | C365: Elco 77ft PT | D365: USA | E365: 65 | F365: 1942-02-28
A366: Cessnock | B366: AM | C366: Bathurst | D366: Australia | E366: 66 | F366: 1942-03-01 | G366: Sydney (90,167)
A367: Little | B367: APD | C367: Wickes APD | D367: USA | E367: 66 | F367: 1942-03-01 | G367: near Bremerton (211,53)
A368: Ramillies | B368: BB | C368: Royal Sovereign | D368: UK | E368: 66 | F368: 1942-03-01 | G368: Cape Town (2,67)
A369: Arrow | B369: DD | C369: 'A' Class | D369: UK | E369: 66 | F369: 1942-03-01 | G369: Aden (20,3)
A370: Thomas Barry | B370: xAP | C370: Grace Line | D370: USA | E370: 66 | F370: 1942-03-01 | G370: near San Diego (225,76)
A371: Oak | B371: ACM | C371: Alder ACM | D371: USA | E371: 67 | F371: 1942-03-02 | G371: near San Diego (225,76)
A372: Admiral Senn | B372: xAK | C372: Isthmian Cargo | D372: USA | E372: 68 | F372: 1942-03-03 | G372: Cristobal (228,101)
A373: Rodman Coleman | B373: xAK | C373: C2-T Cargo | D373: USA | E373: 68 | F373: 1942-03-03 | G373: Balboa (229,102)
A374: S-44 | B374: SS | C374: Electric Boat S-42 | D374: USA | E374: 69 | F374: 1942-03-04 | G374: San Diego (227,78)
A375: British Confidence | B375: TK | C375: Shell Type-A | D375: UK | E375: 69 | F375: 1942-03-04 | G375: Abadan (39,3)
A376: Benledi | B376: xAK | C376: Dominion M Cargo | D376: UK | E376: 69 | F376: 1942-03-04 | G376: Cape Town (2,67)
A377: Denbighshire | B377: xAP | C377: Empire/Glen | D377: UK | E377: 69 | F377: 1942-03-04 | G377: Cape Town (2,67)
... A421: Atlanta | B421: CLAA | C421: Atlanta | D421: USA | E421: 87 | F421: 1942-03-22 | G421: Balboa (229,102)
A422: PT-59 | B422: PT | C422: Elco 77ft PT | D422: USA | E422: 87 | F422: 1942-03-22
A423: Cornish City | B423: xAK | C423: Euro M Cargo | D423: UK | E423: 87 | F423: 1942-03-22 | G423: Aden (20,3)
A424: Hunter Liggett | B424: AP | C424: Harris | D424: USA | E424: 88 | F424: 1942-03-23 | G424: Balboa (229,102)
A425: No. 372 | B425: ML | C425: Fairmile B | D425: UK | E425: 88 | F425: 1942-03-23 | G425: Singapore (50,84)
A426: No. 365 | B426: ML | C426: Fairmile B | D426: UK | E426: 89 | F426: 1942-03-24 | G426: Singapore (50,84)
A427: YMS-95 | B427: YMS | C427: YMS-1 | D427: USA | E427: 89 | F427: 1942-03-24 | G427: near Alameda (219,69)
A428: Canso | B428: AM | C428: Bangor VTE | D428: Canada | E428: 90 | F428: 1942-03-25 | G428: near Victoria (209,49)
A429: Devonshire | B429: CA | C429: London | D429: UK | E429: 90 | F429: 1942-03-25 | G429: Cape Town (2,67)
A430: PT-60 | B430: PT | C430: Elco 77ft PT | D430: USA | E430: 90 | F430: 1942-03-25
A431: Inconstant | B431: DD | C431: 'I' Class | D431: UK | E431: 91 | F431: 1942-03-26 | G431: Cape Town (2,67)
A432: John Adams | B432: xAK | C432: EC2 Liberty Cargo | D432: USA | E432: 91 | F432: 1942-03-26 | G432: Alameda (219,70)
A433: Punjab | B433: AM | C433: Bathurst | D433: India | E433: 93 | F433: 1942-03-28 | G433: Sydney (90,167)
A434: J. Franklin Bell | B434: AP | C434: Harris | D434: USA | E434: 94 | F434: 1942-03-29 | G434: Mare Island (218,69)
A435: Solor | B435: TK | C435: BTC Type-L | D435: Other Allied | E435: 95 | F435: 1942-03-30 | G435: Abadan (39,3)
A436: Birch | B436: ACM | C436: Alder ACM | D436: USA | E436: 96 | F436: 1942-03-31 | G436: near San Diego (225,76)
A437: Camden | B437: TK | C437: Federal Type-E | D437: USA | E437: 96 | F437: 1942-03-31 | G437: Balboa (229,102)
A438: YMS-96 | B438: YMS | C438: YMS-1 | D438: USA | E438: 96 | F438: 1942-03-31 | G438: near Alameda (219,69)
A439: Alcyon | B439: AK | C439: C2 Arcturus | D439: USA | E439: 97 | F439: 1942-04-01 | G439: Balboa (229,102)
A440: Chincoteague | B440: AVD | C440: Barnegat | D440: USA | E440: 97 | F440: 1942-04-01 | G440: near Bremerton (212,52)
A441: Sage | B441: ACM | C441: Alder ACM | D441: USA | E441: 98 | F441: 1942-04-02 | G441: near Bremerton (212,52)
A442: Pakenham | B442: DD | C442: 'P' Class | D442: UK | E442: 98 | F442: 1942-04-02 | G442: Cape Town (2,67)
... A609: SC-518 | B609: SC | C609: SC-453 110' SC | D609: USA | E609: 208 | F609: 1942-07-21 | G609: near Bremerton (212,52)
A610: PT-124 | B610: PT | C610: Elco 80ft PT | D610: USA | E610: 209 | F610: 1942-07-22
A611: SC-709 | B611: SC | C611: SC-453 110' SC | D611: USA | E611: 210 | F611: 1942-07-23 | G611: (227,27)
A612: Thomas Nelson | B612: xAK | C612: EC2 Liberty Cargo | D612: USA | E612: 210 | F612: 1942-07-23 | G612: near San Diego (225,76)
A613: Maridal | B613: xAK | C613: Euro K Cargo | D613: Other Allied | E613: 210 | F613: 1942-07-23 | G613: Aden (20,3)
A614: Gausdal | B614: xAK | C614: Euro M Cargo | D614: Other Allied | E614: 211 | F614: 1942-07-24 | G614: Aden (20,3)
A615: Fletcher | B615: DD | C615: Fletcher HB | D615: USA | E615: 214 | F615: 1942-07-27 | G615: (227,27)
A616: Edwin Markham | B616: xAK | C616: EC2 Liberty Cargo | D616: USA | E616: 214 | F616: 1942-07-27 | G616: Alameda (219,70)
A617: PT-118 | B617: PT | C617: Elco 80ft PT | D617: USA | E617: 215 | F617: 1942-07-28
A618: SC-522 | B618: SC | C618: SC-453 110' SC | D618: USA | E618: 216 | F618: 1942-07-29 | G618: near San Diego (225,76)
A619: Mobilube | B619: TK | C619: T2-SE-A | D619: USA | E619: 216 | F619: 1942-07-29 | G619: Cristobal (228,101)
A620: Conflict | B620: AM | C620: Adroit 173' AM | D620: USA | E620: 217 | F620: 1942-07-30 | G620: (213,56)
A621: Inchkeith | B621: AMc | C621: Isles | D621: New Zealand | E621: 217 | F621: 1942-07-30 | G621: Auckland (115,185)
A622: PC-578 | B622: SC | C622: PC-461 173' SC | D622: USA | E622: 218 | F622: 1942-07-31 | G622: (213,56)
A623: Killegray | B623: AMc | C623: Isles | D623: New Zealand | E623: 219 | F623: 1942-08-01 | G623: Auckland (115,185)
A624: Skylark | B624: AM | C624: Auk | D624: USA | E624: 220 | F624: 1942-08-02 | G624: Alameda (219,70)
A625: Rimu | B625: AMc | C625: Castle Trawler | D625: New Zealand | E625: 220 | F625: 1942-08-02 | G625: Auckland (115,185)
A626: Rezkij | B626: DD | C626: Gnevnyi | D626: nation 13 | E626: 221 | F626: 1942-08-03 | G626: near Yenki (112,46)
A627: Juan Cabrillo | B627: xAK | C627: EC2 Liberty Cargo | D627: USA | E627: 221 | F627: 1942-08-03 | G627: Alameda (219,70)
A628: Igonish | B628: AM | C628: Bangor VTE | D628: Canada | E628: 222 | F628: 1942-08-04 | G628: near Victoria (209,49)
A629: James Schureman | B629: xAK | C629: EC2 Liberty Cargo | D629: USA | E629: 222 | F629: 1942-08-04 | G629: Alameda (219,70)
... A631: SC-702 | B631: SC | C631: SC-453 110' SC | D631: USA | E631: 224 | F631: 1942-08-06 | G631: (227,27)
A632: PT-125 | B632: PT | C632: Elco 80ft PT | D632: USA | E632: 225 | F632: 1942-08-07
A633: Sanda | B633: AMc | C633: Isles | D633: New Zealand | E633: 226 | F633: 1942-08-08 | G633: Auckland (115,185)
A634: YMS-130 | B634: YMS | C634: YMS-1 | D634: USA | E634: 226 | F634: 1942-08-08 | G634: near Bremerton (211,53)
A635: YMS-114 | B635: YMS | C635: YMS-1 | D635: USA | E635: 227 | F635: 1942-08-09 | G635: San Diego (227,78)
A636: Nicholas | B636: DD | C636: Fletcher HB | D636: USA | E636: 228 | F636: 1942-08-10 | G636: (227,27)
A637: PT-119 | B637: PT | C637: Elco 80ft PT | D637: USA | E637: 228 | F637: 1942-08-10
A638: Bengal | B638: AM | C638: Bathurst | D638: India | E638: 229 | F638: 1942-08-11 | G638: Sydney (90,167)
A639: Scarba | B639: AMc | C639: Isles | D639: New Zealand | E639: 229 | F639: 1942-08-11 | G639: Auckland (115,185)
A640: Frobisher | B640: CA | C640: Frobisher | D640: UK | E640: 229 | F640: 1942-08-11 | G640: Aden (20,3)
A641: YMS-133 | B641: YMS | C641: YMS-1 | D641: USA | E641: 229 | F641: 1942-08-11 | G641: near Bremerton (211,53)
A642: Cascade | B642: AD | C642: Dixie | D642: USA | E642: 230 | F642: 1942-08-12 | G642: Balboa (229,102)
A643: PT-120 | B643: PT | C643: Elco 80ft PT | D643: USA | E643: 230 | F643: 1942-08-12
A644: PT-121 | B644: PT | C644: Elco 80ft PT | D644: USA | E644: 230 | F644: 1942-08-12
A645: SC-703 | B645: SC | C645: SC-453 110' SC | D645: USA | E645: 230 | F645: 1942-08-12 | G645: (227,27)
A646: SC-704 | B646: SC | C646: SC-453 110' SC | D646: USA | E646: 230 | F646: 1942-08-12 | G646: (227,27)
A647: Albacore | B647: SS | C647: Gato | D647: USA | E647: 231 | F647: 1942-08-13 | G647: Balboa (229,102)
A648: Broome | B648: AM | C648: Bathurst | D648: Australia | E648: 232 | F648: 1942-08-14 | G648: Brisbane (96,160)
A649: Prometheus | B649: AR | C649: Prometheus | D649: USA | E649: 232 | F649: 1942-08-14
A650: Lansdowne | B650: DD | C650: Bristol | D650: USA | E650: 232 | F650: 1942-08-14 | G650: Cristobal (228,101)
A651: SC-700 | B651: SC | C651: SC-453 110' SC | D651: USA | E651: 232 | F651: 1942-08-14 | G651: (227,27)
A652: Kingfish | B652: SS | C652: Gato | D652: USA | E652: 232 | F652: 1942-08-14 | G652: (227,27)
A653: Trevaylor | B653: xAK | C653: Euro M Cargo | D653: UK | E653: 232 | F653: 1942-08-14 | G653: Cape Town (2,67)
A654: South Dakota | B654: BB | C654: South Dakota | D654: USA | E654: 233 | F654: 1942-08-15 | G654: (227,27)
A655: Gillespie | B655: DD | C655: Benson | D655: USA | E655: 233 | F655: 1942-08-15 | G655: San Francisco (218,70)
A656: SC-520 | B656: SC | C656: SC-453 110' SC | D656: USA | E656: 233 | F656: 1942-08-15 | G656: near San Diego (225,76)
A657: SC-705 | B657: SC | C657: SC-453 110' SC | D657: USA | E657: 234 | F657: 1942-08-16 | G657: Balboa (229,102)
A658: SC-708 | B658: SC | C658: SC-453 110' SC | D658: USA | E658: 235 | F658: 1942-08-17 | G658: (227,27)
A659: William M. Stewart | B659: xAK | C659: EC2 Liberty Cargo | D659: USA | E659: 235 | F659: 1942-08-17 | G659: (213,56)
A660: City of Adelaide | B660: xAK | C660: Dominion M Cargo | D660: UK | E660: 235 | F660: 1942-08-17 | G660: Cape Town (2,67)
...

Sheet Notes
A1: How this was decoded
A2: Source: the 25 Dec incoming file, plus the earlier saves for loss dates. Only records with the Allied side flag were read.
A3: Confirmed against the turn reports: ship names, class, type, nation, captain, fuel, endurance, TF membership, TF home/destination, current hex, port, sunk status, arrival countdown.
A4: Inferred, not confirmed: the damage columns. The order is fire, system, float, float (major), engine, engine (major). It matches ships reported hit (e.g. Duntroon on fire, Elisavet torpedoed).
A5: Inferred, not confirmed: 'Crew exp'.
A6: Mission names marked (?) are inferred from what ships the TF contains; unmarked ones were matched to report messages.
A7: Place names come from the turn reports; the save stores bases as coordinates only. 'near X' means within 2 hexes of a named place. Blank = no name found; use the hex coordinates.
A8: Fuel % uses the class maximum from the save's ship-class table.
